Workbook

Sheet Executive Report
A1: HHU LEDERRAPPORT 2026
A2: September YTD + Q4-prognose | 3–30–300 beslutningsvisning
A4: HELÅRSPROGNOSE | D4: SLUTTAVVIK (VAC) | G4: ÅRSVERK | J4: EVM EFFEKTIVITET | M4: STUDENTER
A5: =SUM(FactGL[Belop_signert]) -> 129631567 | D5: =SUM(FactBudget[BudsjettBelop])-SUM(FactGL[Belop_signert]) -> 522258 | G5: =SUMIFS(FactFTE[Aarsverk_Totalt],FactFTE[DatoNokkel],202612) -> 229 | J5: =MAX(FactEVM[CostPerformanceIndex_CPI]) -> 0.97 | M5: =SUMIFS(FactStudents_2027[RegistrerteStudenter],FactStudents_2027[DatoNokkel],20271031) -> 3450
A7: ="Budsjett "&TEXT(SUM(FactBudget[BudsjettBelop])/1000000,"0.0")&" MNOK" -> Budsjett 130.2 MNOK | D7: =IF(D5>=0,"🟢 Innenfor budsjett",IF(D5/SUM(FactBudget[BudsjettBelop])>=-5%,"🟡 Moderat avvik","🔴 Kritisk avvik")) -> 🟢 Innenfor budsjett | G7: =TEXT(SUMIFS(FactFTE[Aarsverk_UF],FactFTE[DatoNokkel],202612),"0")&" UF / "&TEXT(SUMIFS(FactFTE[Aarsverk_TA],FactFTE[DatoNokkel],202612),"0")&" TA" -> 154 UF / 75 TA | J7: ="🟡 CPI "&TEXT(J5,"0.00")&" | SPI "&TEXT(MAX(FactEVM[SchedulePerformanceIndex_SPI]),"0.00") -> 🟡 CPI 0.97 | SPI 0.98 | M7: =TEXT(SUMIFS(FactStudents_2027[SPE60],FactStudents_2027[DatoNokkel],20271031),"#,##0")&" SPE60 | "&TEXT(M5/SUMIFS(FactFTE_2027[Aarsverk_UF],FactFTE_2027[DatoNokkel],20271231),"0.0")&" stud./UF" -> 3,153 SPE60 | 22.3 stud./UF
A9: Visual RAG: grønn = innenfor plan | gul = 0–5 % over plan | rød = >5 % over plan
A10: Månedsutvikling: regnskap/prognose mot budsjett | J10: Sluttavvik per enhet
A27: LEDELSESKONKLUSJON
A28: 2026 ventes 0,52 MNOK innenfor budsjett, drevet av 1,15 MNOK mindreforbruk i Rettsvitenskap. Økonomi ligger 0,71 MNOK over plan, og EVM-indeksene CPI 0,97 / SPI 0,98 viser fortsatt moderat gjennomføringsrisiko. Prioriter BOA-frikjøp, EVU-kontroll og bemanningsstyring før årsavslutningen.
A32: Datagrunnlag: alle 432 budsjettlinjer, 433 GL-linjer, 48 FTE-rader og 12 studentrader.
A34: RAG: 🟢 innenfor mål | 🟡 moderat avvik / oppfølging | 🔴 kritisk avvik

Sheet Unit Analysis
A1: ENHETS- OG TILTAKSANALYSE 2026
A2: Avvik, bemanning og gjennomføring — full dekning av HHUs fire budsjettansvarsområder
A4: OrgKode | B4: Enhet | C4: Budsjett | D4: LE / helår | E4: Sluttavvik | F4: Avvik % | G4: UF-ÅV | H4: TA-ÅV | I4: Totale ÅV | J4: RAG
A5: K10000 | B5: Fakultetsadministrasjon & Felles | C5: =SUMIFS(FactBudget[BudsjettBelop],FactBudget[OrgKode],A5) -> 14000000 | D5: =SUMIFS(FactGL[Belop_signert],FactGL[OrgKode],A5) -> 13912501 | E5: =C5-D5 -> 87499 | F5: =E5/C5 -> 0.0062499286 | G5: =SUMIFS(FactFTE[Aarsverk_UF],FactFTE[OrgKode],A5,FactFTE[DatoNokkel],202612) -> 0 | H5: =SUMIFS(FactFTE[Aarsverk_TA],FactFTE[OrgKode],A5,FactFTE[DatoNokkel],202612) -> 22 | I5: =G5+H5 -> 22 | J5: =IF(F5>=0,"🟢 Innenfor",IF(F5>=-5%,"🟡 Følg opp","🔴 Kritisk")) -> 🟢 Innenfor
A6: K11000 | B6: Ledelse og innovasjon | C6: =SUMIFS(FactBudget[BudsjettBelop],FactBudget[OrgKode],A6) -> 38500000 | D6: =SUMIFS(FactGL[Belop_signert],FactGL[OrgKode],A6) -> 38503496 | E6: =C6-D6 -> -3496 | F6: =E6/C6 -> -9.0805195e-05 | G6: =SUMIFS(FactFTE[Aarsverk_UF],FactFTE[OrgKode],A6,FactFTE[DatoNokkel],202612) -> 45 | H6: =SUMIFS(FactFTE[Aarsverk_TA],FactFTE[OrgKode],A6,FactFTE[DatoNokkel],202612) -> 18 | I6: =G6+H6 -> 63 | J6: =IF(F6>=0,"🟢 Innenfor",IF(F6>=-5%,"🟡 Følg opp","🔴 Kritisk")) -> 🟡 Følg opp
A7: K12000 | B7: Rettsvitenskap | C7: =SUMIFS(FactBudget[BudsjettBelop],FactBudget[OrgKode],A7) -> 29250000 | D7: =SUMIFS(FactGL[Belop_signert],FactGL[OrgKode],A7) -> 28101060 | E7: =C7-D7 -> 1148940 | F7: =E7/C7 -> 0.03928 | G7: =SUMIFS(FactFTE[Aarsverk_UF],FactFTE[OrgKode],A7,FactFTE[DatoNokkel],202612) -> 34 | H7: =SUMIFS(FactFTE[Aarsverk_TA],FactFTE[OrgKode],A7,FactFTE[DatoNokkel],202612) -> 12 | I7: =G7+H7 -> 46 | J7: =IF(F7>=0,"🟢 Innenfor",IF(F7>=-5%,"🟡 Følg opp","🔴 Kritisk")) -> 🟢 Innenfor
A8: K13000 | B8: Økonomi | C8: =SUMIFS(FactBudget[BudsjettBelop],FactBudget[OrgKode],A8) -> 48403825 | D8: =SUMIFS(FactGL[Belop_signert],FactGL[OrgKode],A8) -> 49114510 | E8: =C8-D8 -> -710685 | F8: =E8/C8 -> -0.014682414 | G8: =SUMIFS(FactFTE[Aarsverk_UF],FactFTE[OrgKode],A8,FactFTE[DatoNokkel],202612) -> 75 | H8: =SUMIFS(FactFTE[Aarsverk_TA],FactFTE[OrgKode],A8,FactFTE[DatoNokkel],202612) -> 23 | I8: =G8+H8 -> 98 | J8: =IF(F8>=0,"🟢 Innenfor",IF(F8>=-5%,"🟡 Følg opp","🔴 Kritisk")) -> 🟡 Følg opp
A11: TILTAK — FORVENTET MOT REALISERT
A12: Tiltak | B12: Enhet | C12: Tiltaksnavn | D12: Forventet | E12: Realisert | F12: Grad | G12: Status | H12: Frist
A13: T001_HHU | B13: K10000 | C13: Frys i ikke-kritisk administrativ rekruttering (TA) | D13: 1200000 | E13: 950000 | F13: =E13/D13 -> 0.79166667 | G13: =IF(F13>=100%,"🟢 Fullført",IF(F13>=75%,"🟡 Følg opp","🔴 Kritisk gap")) -> 🟡 Følg opp | H13: 46387
A14: T002_HHU | B14: K13000 | C14: Økt overføring av vitenskapelig tid til BOA frikjøp (NFR/EU) | D14: 1800000 | E14: 1400000 | F14: =E14/D14 -> 0.77777778 | G14: =IF(F14>=100%,"🟢 Fullført",IF(F14>=75%,"🟡 Følg opp","🔴 Kritisk gap")) -> 🟡 Følg opp | H14: 46387
A15: T003_HHU | B15: K11000 | C15: Lønnsomhetskorrigering og prosjektkontroll på EVU001 (SRS 9) | D15: 800000 | E15: 450000 | F15: =E15/D15 -> 0.5625 | G15: =IF(F15>=100%,"🟢 Fullført",IF(F15>=75%,"🟡 Følg opp","🔴 Kritisk gap")) -> 🔴 Kritisk gap | H15: 46356
A16: T004_HHU | B16: K12000 | C16: Midlertidig vakanshold av professorhjemmel i Q2-Q3 | D16: 800000 | E16: 800000 | F16: =E16/D16 -> 1 | G16: =IF(F16>=100%,"🟢 Fullført",IF(F16>=75%,"🟡 Følg opp","🔴 Kritisk gap")) -> 🟢 Fullført | H16: 46295
A19: ANALYTISK KONKLUSJON
A20: Rettsvitenskap er hoveddriveren bak positivt sluttavvik (+1,15 MNOK), mens Økonomi har størst oppfølgingsbehov (–0,71 MNOK). Tiltakene har realisert 3,60 av 4,60 MNOK (78,3 %). De største gjenstående gapene ligger i BOA-frikjøp (0,40 MNOK) og EVU-kontroll (0,35 MNOK).
A24: RAG: budsjettavvik ≥0 % grønt, 0 til −5 % gult, <−5 % rødt | tiltak ≥100 % grønt, 75–99,9 % gult, <75 % rødt

Sheet Variance Actions
A1: DETALJERT AVVIKSANALYSE OG HANDLINGSPLAN
A2: HHU 2026 Latest Estimate | Fra totalavvik til rotårsak, tiltak og ansvar
A4: Netto sluttavvik | C4: Positive drivere | E4: Negative drivere | G4: Tiltaksgap | I4: Største risiko
A5: =SUM(FactBudget[BudsjettBelop])-SUM(FactGL[Belop_signert]) -> 522258 | C5: =SUMIF(F11:F21,">0",F11:F21) -> 2107632 | E5: =SUMIF(F11:F21,"<0",F11:F21) -> -1585374 | G5: =SUM(FactAction[ForventetInnsparingNOK])-SUM(FactAction[RealisertInnsparingNOK]) -> 1000000 | I5: K13000 lønn
A9: 1. AVVIKSDRIVERE — BUDSJETT MINUS LATEST ESTIMATE | J9: 2. MÅNEDSHOTSPOTS
A10: OrgKode | B10: Konto | C10: Driver | D10: Budsjett | E10: LE | F10: Avvik | G10: Avvik % | H10: RAG | J10: Måned | K10: Netto avvik | L10: Forklaring
A11: K13000 | B11: 5000 | C11: Fast lønn | D11: =SUMIFS(FactBudget[BudsjettBelop],FactBudget[OrgKode],A11,FactBudget[Konto],B11) -> 28074218 | E11: =SUMIFS(FactGL[Belop_signert],FactGL[OrgKode],A11,FactGL[Konto],B11) -> 29056814 | F11: =D11-E11 -> -982596 | G11: =IFERROR(F11/D11,IF(F11<0,-1,0)) -> -0.034999942 | H11: =IF(F11>=0,"🟢 Favorabel",IF(G11>=-5%,"🟡 Moderat","🔴 Kritisk")) -> 🟡 Moderat | J11: Juni | K11: -356048 | L11: Feriepenger + lønnseffekt
A12: K12000 | B12: 5000 | C12: Fast lønn | D12: =SUMIFS(FactBudget[BudsjettBelop],FactBudget[OrgKode],A12,FactBudget[Konto],B12) -> 16965000 | E12: =SUMIFS(FactGL[Belop_signert],FactGL[OrgKode],A12,FactGL[Konto],B12) -> 16286400 | F12: =D12-E12 -> 678600 | G12: =IFERROR(F12/D12,IF(F12<0,-1,0)) -> 0.04 | H12: =IF(F12>=0,"🟢 Favorabel",IF(G12>=-5%,"🟡 Moderat","🔴 Kritisk")) -> 🟢 Favorabel | J12: September | K12: -278427 | L12: EVU001-avsetning + AACSB
A13: K13000 | B13: 5080 | C13: Feriepenger | D13: =SUMIFS(FactBudget[BudsjettBelop],FactBudget[OrgKode],A13,FactBudget[Konto],B13) -> 3388268 | E13: =SUMIFS(FactGL[Belop_signert],FactGL[OrgKode],A13,FactGL[Konto],B13) -> 2980829 | F13: =D13-E13 -> 407439 | G13: =IFERROR(F13/D13,IF(F13<0,-1,0)) -> 0.12024993 | H13: =IF(F13>=0,"🟢 Favorabel",IF(G13>=-5%,"🟡 Moderat","🔴 Kritisk")) -> 🟢 Favorabel | J13: Desember | K13: 120576 | L13: Normal Q4-prognose
A14: K11000 | B14: 5080 | C14: Feriepenger | D14: =SUMIFS(FactBudget[BudsjettBelop],FactBudget[OrgKode],A14,FactBudget[Konto],B14) -> 2695000 | E14: =SUMIFS(FactGL[Belop_signert],FactGL[OrgKode],A14,FactGL[Konto],B14) -> 2290746 | F14: =D14-E14 -> 404254 | G14: =IFERROR(F14/D14,IF(F14<0,-1,0)) -> 0.15000148 | H14: =IF(F14>=0,"🟢 Favorabel",IF(G14>=-5%,"🟡 Moderat","🔴 Kritisk")) -> 🟢 Favorabel | J14: Øvrige måneder | K14: 1013193 | L14: Stabile, hovedsakelig favorable
A15: K12000 | B15: 5080 | C15: Feriepenger | D15: =SUMIFS(FactBudget[BudsjettBelop],FactBudget[OrgKode],A15,FactBudget[Konto],B15) -> 2047500 | E15: =SUMIFS(FactGL[Belop_signert],FactGL[OrgKode],A15,FactGL[Konto],B15) -> 1670760 | F15: =D15-E15 -> 376740 | G15: =IFERROR(F15/D15,IF(F15<0,-1,0)) -> 0.184 | H15: =IF(F15>=0,"🟢 Favorabel",IF(G15>=-5%,"🟡 Moderat","🔴 Kritisk")) -> 🟢 Favorabel
A16: K11000 | B16: 7790 | C16: EVU001 tapsavsetning | D16: =SUMIFS(FactBudget[BudsjettBelop],FactBudget[OrgKode],A16,FactBudget[Konto],B16) -> 0 | E16: =SUMIFS(FactGL[Belop_signert],FactGL[OrgKode],A16,FactGL[Konto],B16) -> 350000 | F16: =D16-E16 -> -350000 | G16: =IFERROR(F16/D16,IF(F16<0,-1,0)) -> -1 | H16: =IF(F16>=0,"🟢 Favorabel",IF(G16>=-5%,"🟡 Moderat","🔴 Kritisk")) -> 🔴 Kritisk
A17: K10000 | B17: 5080 | C17: Feriepenger | D17: =SUMIFS(FactBudget[BudsjettBelop],FactBudget[OrgKode],A17,FactBudget[Konto],B17) -> 980000 | E17: =SUMIFS(FactGL[Belop_signert],FactGL[OrgKode],A17,FactGL[Konto],B17) -> 833001 | F17: =D17-E17 -> 146999 | G17: =IFERROR(F17/D17,IF(F17<0,-1,0)) -> 0.14999898 | H17: =IF(F17>=0,"🟢 Favorabel",IF(G17>=-5%,"🟡 Moderat","🔴 Kritisk")) -> 🟢 Favorabel
A18: K13000 | B18: 5400 | C18: Arbeidsgiveravgift | D18: =SUMIFS(FactBudget[BudsjettBelop],FactBudget[OrgKode],A18,FactBudget[Konto],B18) -> 3872306 | E18: =SUMIFS(FactGL[Belop_signert],FactGL[OrgKode],A18,FactGL[Konto],B18) -> 4007834 | F18: =D18-E18 -> -135528 | G18: =IFERROR(F18/D18,IF(F18<0,-1,0)) -> -0.0349993 | H18: =IF(F18>=0,"🟢 Favorabel",IF(G18>=-5%,"🟡 Moderat","🔴 Kritisk")) -> 🟡 Moderat
A19: K12000 | B19: 5400 | C19: Arbeidsgiveravgift | D19: =SUMIFS(FactBudget[BudsjettBelop],FactBudget[OrgKode],A19,FactBudget[Konto],B19) -> 2340000 | E19: =SUMIFS(FactGL[Belop_signert],FactGL[OrgKode],A19,FactGL[Konto],B19) -> 2246400 | F19: =D19-E19 -> 93600 | G19: =IFERROR(F19/D19,IF(F19<0,-1,0)) -> 0.04 | H19: =IF(F19>=0,"🟢 Favorabel",IF(G19>=-5%,"🟡 Moderat","🔴 Kritisk")) -> 🟢 Favorabel
A20: K10000 | B20: 6700 | C20: AACSB konsulentkostnad | D20: =SUMIFS(FactBudget[BudsjettBelop],FactBudget[OrgKode],A20,FactBudget[Konto],B20) -> 420000 | E20: =SUMIFS(FactGL[Belop_signert],FactGL[OrgKode],A20,FactGL[Konto],B20) -> 479500 | F20: =D20-E20 -> -59500 | G20: =IFERROR(F20/D20,IF(F20<0,-1,0)) -> -0.14166667 | H20: =IF(F20>=0,"🟢 Favorabel",IF(G20>=-5%,"🟡 Moderat","🔴 Kritisk")) -> 🔴 Kritisk
A21: K11000 | B21: 5100 | C21: Midlertidig lønn / timelærere | D21: =SUMIFS(FactBudget[BudsjettBelop],FactBudget[OrgKode],A21,FactBudget[Konto],B21) -> 1540000 | E21: =SUMIFS(FactGL[Belop_signert],FactGL[OrgKode],A21,FactGL[Konto],B21) -> 1597750 | F21: =D21-E21 -> -57750 | G21: =IFERROR(F21/D21,IF(F21<0,-1,0)) -> -0.0375 | H21: =IF(F21>=0,"🟢 Favorabel",IF(G21>=-5%,"🟡 Moderat","🔴 Kritisk")) -> 🟡 Moderat
A24: 3. PRIORITERT HANDLINGSPLAN
A25: Prioritet | B25: Område | C25: Rotårsak / observasjon | D25: Anbefalt handling | E25: Eier | F25: Frist | G25: Brutto gap | H25: Forventet effekt | I25: KPI / kontrollpunkt | J25: RAG | K25: Beslutning nå | L25: Oppfølging
A26: 1 | B26: K13000 Økonomi | C26: Fast lønn og AGA gir 1,12 MNOK merforbruk før feriepengeeffekt. | D26: Lås nyansettelser uten finansiering; realiser resterende BOA-frikjøp og månedlig avstem lønnsfil mot UBW. | E26: Instituttleder Økonomi | F26: 46356 | G26: 1118124 | H26: 710685 | I26: Månedlig lønnsavvik ≤ 0; T002 realisering 100 % | J26: 🔴 Høy | K26: Godkjenn lønns- og BOA-tiltaksplan | L26: Ukentlig til gap <0,2 MNOK
A27: 2 | B27: K11000 Ledelse/innovasjon | C27: EVU001 tapsavsetning 0,35 MNOK og 0,06 MNOK ekstra midlertidig lønn. | D27: Fullfør EVU-lønnsomhetsanalyse, revider kontraktsmargin og stopp nye leveranser uten dokumentert dekningsbidrag. | E27: Instituttleder Ledelse | F27: 46326 | G27: 407750 | H27: 350000 | I27: T003 realisering 100 %; EVU DB ≥ 0 | J27: 🔴 Høy | K27: Beslutt korrigert EVU-scope/pris | L27: Annenhver uke
A28: 3 | B28: K12000 Rettsvitenskap | C28: Vakans og lavere lønnsrelaterte kostnader gir 1,15 MNOK mindreforbruk. | D28: Beskytt besparelsen; tillat bare kritiske ansettelser og vurder faglig kapasitetsrisiko før permanent reduksjon. | E28: Instituttleder Rettsvitenskap | F28: 46371 | G28: 0 | H28: 1148940 | I28: VAC ≥ +0,8 MNOK og forsvarlig undervisningskapasitet | J28: 🟢 Sikre | K28: Bekreft rekrutteringsplan 2027 | L28: Månedlig
A29: 4 | B29: K10000 Administrasjon | C29: AACSB-konsulentkostnad er 0,06 MNOK over plan, delvis motvirket av lavere feriepenger. | D29: Fastsett gjenværende AACSB-scope og innfør endringsgodkjenning for tilleggstimer. | E29: Fakultetsdirektør | F29: 46310 | G29: 59500 | H29: 59500 | I29: Ingen nye ikke-godkjente konsulenttimer | J29: 🟡 Moderat | K29: Godkjenn kostnadstak | L29: Ved hver bestilling
A30: 5 | B30: Tiltaksportefølje | C30: Samlet urealisert tiltaksgap er 1,00 MNOK; T003 har lavest grad på 56,3 %. | D30: Etabler én samlet lukkeplan for T001–T003 med ukentlig eierstatus, beløpsbevis og eskalering ved manglende fremdrift. | E30: Fakultetsdirektør | F30: 46302 | G30: 1000000 | H30: 1000000 | I30: Realisert grad ≥ 90 % innen november | J30: 🔴 Høy | K30: Mandater ukentlig tiltakstavle | L30: Ukentlig
A33: LEDELSESVURDERING
A34: Nettoresultatet er positivt, men robustheten er svak: 1,15 MNOK i vakansbesparelse ved Rettsvitenskap dekker i stor grad lønnsmerforbruket i Økonomi og avvik knyttet til EVU/AACSB. Ledelsen bør derfor ikke tolke +0,52 MNOK som strukturelt handlingsrom. Første prioritet er å lukke lønns- og BOA-gapet i K13000; andre prioritet er å stoppe videre marginerosjon i EVU001. Besparelsen i K12000 bør beholdes som buffer inntil disse risikoene er lukket.

Sheet 2027 Plan Report
A1: HHU BUDSJETT- OG KAPASITETSPLAN 2027
A2: Driverbasert plan | økonomi, bemanning, utdanning og tiltak
A4: INNTEKTER | D4: KOSTNADER | G4: NETTO RESULTAT | J4: LØNNSANDEL | M4: STUDENTER
A5: {=SUM(SUMIFS(FactBudget_2027[BudsjettBelop],FactBudget_2027[Konto],{3900,3670,3600,3630,3400,3420}))} -> 2.8607e+08 | D5: =SUM(FactBudget_2027[BudsjettBelop])-A5 -> 2.82e+08 | G5: =A5-D5 -> 4069999.7 | J5: {=SUM(SUMIFS(FactBudget_2027[BudsjettBelop],FactBudget_2027[Konto],{5000,5400}))/A5} -> 0.66766875 | M5: =SUMIFS(FactStudents_2027[RegistrerteStudenter],FactStudents_2027[DatoNokkel],20271031) -> 3450
A7: 🔴 2,0 MNOK under dokumentert ramme | D7: 282,0 MNOK plan | G7: 🟡 Positiv, men 2,0 MNOK under mål | J7: 🔴 Over mål 64,5 % | M7: 3 153 SPE60 | 22,3 stud./UF
A10: ØKONOMI OG KAPASITET PER ENHET
A11: OrgKode | B11: Enhet | C11: Inntekter | D11: Kostnader | E11: Netto | F11: ÅV | G11: UF-ÅV | H11: Studenter | I11: SPE60 | K11: Tiltak | L11: Enhet | M11: Effekt | N11: Status | O11: Beslutningsdriver
A12: K10000 | B12: Fakultetsadministrasjon & Felles | C12: {=SUM(SUMIFS(FactBudget_2027[BudsjettBelop],FactBudget_2027[OrgKode],A12,FactBudget_2027[Konto],{3900,3670,3600,3630,3400,3420}))} -> 14769850 | D12: =SUMIFS(FactBudget_2027[BudsjettBelop],FactBudget_2027[OrgKode],A12)-C12 -> 14500000 | E12: =C12-D12 -> 269850 | F12: =SUMIFS(FactFTE_2027[Aarsverk_Totalt],FactFTE_2027[OrgKode],A12,FactFTE_2027[DatoNokkel],20271231) -> 28.95 | G12: =SUMIFS(FactFTE_2027[Aarsverk_UF],FactFTE_2027[OrgKode],A12,FactFTE_2027[DatoNokkel],20271231) -> 5 | H12: =SUMIFS(FactStudents_2027[RegistrerteStudenter],FactStudents_2027[OrgKode],A12,FactStudents_2027[DatoNokkel],20271031) -> 0 | I12: =SUMIFS(FactStudents_2027[SPE60],FactStudents_2027[OrgKode],A12,FactStudents_2027[DatoNokkel],20271031) -> 0 | K12: T001 | L12: K10000 | M12: 1800000 | N12: 🟢 Gjennomført | O12: Vakans / lønn
A13: K11000 | B13: Ledelse og innovasjon | C13: {=SUM(SUMIFS(FactBudget_2027[BudsjettBelop],FactBudget_2027[OrgKode],A13,FactBudget_2027[Konto],{3900,3670,3600,3630,3400,3420}))} -> 80000000 | D13: =SUMIFS(FactBudget_2027[BudsjettBelop],FactBudget_2027[OrgKode],A13)-C13 -> 78000000 | E13: =C13-D13 -> 2000000 | F13: =SUMIFS(FactFTE_2027[Aarsverk_Totalt],FactFTE_2027[OrgKode],A13,FactFTE_2027[DatoNokkel],20271231) -> 60.79 | G13: =SUMIFS(FactFTE_2027[Aarsverk_UF],FactFTE_2027[OrgKode],A13,FactFTE_2027[DatoNokkel],20271231) -> 45 | H13: =SUMIFS(FactStudents_2027[RegistrerteStudenter],FactStudents_2027[OrgKode],A13,FactStudents_2027[DatoNokkel],20271031) -> 1150 | I13: =SUMIFS(FactStudents_2027[SPE60],FactStudents_2027[OrgKode],A13,FactStudents_2027[DatoNokkel],20271031) -> 1050 | K13: T002 | L13: K13000 | M13: 1500000 | N13: 🟢 I rute | O13: Faglig reallokering
A14: K12000 | B14: Rettsvitenskap | C14: {=SUM(SUMIFS(FactBudget_2027[BudsjettBelop],FactBudget_2027[OrgKode],A14,FactBudget_2027[Konto],{3900,3670,3600,3630,3400,3420}))} -> 62000000 | D14: =SUMIFS(FactBudget_2027[BudsjettBelop],FactBudget_2027[OrgKode],A14)-C14 -> 61000000 | E14: =C14-D14 -> 999999.96 | F14: =SUMIFS(FactFTE_2027[Aarsverk_Totalt],FactFTE_2027[OrgKode],A14,FactFTE_2027[DatoNokkel],20271231) -> 48.25 | G14: =SUMIFS(FactFTE_2027[Aarsverk_UF],FactFTE_2027[OrgKode],A14,FactFTE_2027[DatoNokkel],20271231) -> 38 | H14: =SUMIFS(FactStudents_2027[RegistrerteStudenter],FactStudents_2027[OrgKode],A14,FactStudents_2027[DatoNokkel],20271031) -> 850 | I14: =SUMIFS(FactStudents_2027[SPE60],FactStudents_2027[OrgKode],A14,FactStudents_2027[DatoNokkel],20271031) -> 788 | K14: T003 | L14: K11000 | M14: 1400000 | N14: 🟢 I rute | O14: EVU-inntekt
A15: K13000 | B15: Økonomi | C15: {=SUM(SUMIFS(FactBudget_2027[BudsjettBelop],FactBudget_2027[OrgKode],A15,FactBudget_2027[Konto],{3900,3670,3600,3630,3400,3420}))} -> 1.2930015e+08 | D15: =SUMIFS(FactBudget_2027[BudsjettBelop],FactBudget_2027[OrgKode],A15)-C15 -> 1.285e+08 | E15: =C15-D15 -> 800149.68 | F15: =SUMIFS(FactFTE_2027[Aarsverk_Totalt],FactFTE_2027[OrgKode],A15,FactFTE_2027[DatoNokkel],20271231) -> 83.95 | G15: =SUMIFS(FactFTE_2027[Aarsverk_UF],FactFTE_2027[OrgKode],A15,FactFTE_2027[DatoNokkel],20271231) -> 67 | H15: =SUMIFS(FactStudents_2027[RegistrerteStudenter],FactStudents_2027[OrgKode],A15,FactStudents_2027[DatoNokkel],20271031) -> 1450 | I15: =SUMIFS(FactStudents_2027[SPE60],FactStudents_2027[OrgKode],A15,FactStudents_2027[DatoNokkel],20271031) -> 1315 | K15: T004 | L15: K13000 | M15: 1800000 | N15: 🟢 I rute | O15: TDI / BOA
A17: Diagrammet viser nivåer (nøytral palett); RAG brukes på nettoresultat og måloppnåelse i tabell/KPI-kort.
A18: Inntekter og kostnader per enhet | K18: BESLUTNINGSSTØTTE
K19: 1. Avklar manglende 2,0 MNOK inntekt før budsjettet publiseres. 2. Konto-basert lønnsandel er 66,8 %, over mål 64,5 %; avstem mot FTE-filens 63,9 %. 3. Beskytt tiltak T003/T004: 3,2 MNOK inntektsvekst fra EVU og BOA er nødvendig for handlingsrommet. 4. K13000 bærer 45 % av inntektene og krever tett prosjekt- og kapasitetsstyring.
A35: RAG: grønt = mål oppfylt | gult = moderat avvik som krever oppfølging | rødt = målbrudd eller kritisk datagap

Sheet Budget Process 2027
A1: BUDSJETTPROSESS 2027 — STYRING, ANALYSE OG BESLUTNINGER
A2: Handelshøyskolen ved UiA | Fra rammeforutsetninger til systemfrys og løpende prognose
A4: INNTEKTER | D4: KOSTNADER | G4: RESULTAT | J4: LØNNSANDEL | M4: ÅRSVERK
A5: {=SUM(SUMIFS(FactBudget_2027[BudsjettBelop],FactBudget_2027[Konto],{3900,3670,3600,3630,3400,3420}))} -> 2.8607e+08 | D5: =SUM(FactBudget_2027[BudsjettBelop])-A5 -> 2.82e+08 | G5: =A5-D5 -> 4069999.7 | J5: {=SUM(SUMIFS(FactBudget_2027[BudsjettBelop],FactBudget_2027[Konto],{5000,5400}))/A5} -> 0.66766875 | M5: =SUMIFS(FactFTE_2027[Aarsverk_Totalt],FactFTE_2027[DatoNokkel],20271231) -> 221.94
A7: 🔴 2,0 MNOK under dokumentert ramme | D7: 282,0 MNOK | G7: 🟡 Positivt, men under målet | J7: 🟡 66,8 % mot mål ≤64,5 % | M7: 230 planlagt | 3,5 % vakans
A10: 1. PROSESSKART OG BESLUTNINGSPORTER
A11: Fase | B11: Tidspunkt | C11: Hovedspørsmål | D11: Nøkkelaktiviteter | E11: Datagrunnlag | F11: Ansvarlig | G11: Leveranse | H11: Beslutningsport | I11: Status | J11: RAG | K11: Kontroll | L11: Avhengighet | M11: Neste handling | N11: Frist
A12: 1 | B12: 46266 | C12: Hva er bindende ramme? | D12: Avstem KD-/UiA-ramme, kontoplan og versjon | E12: Tildelingsbrev, BUD2026 | F12: Senior Controller | G12: Rammebrev og forutsetningsnotat | H12: Ramme godkjent | I12: Nesten ferdig | J12: 🟡 | K12: Én signert rammeversjon | L12: Sentral økonomi | M12: Avklar 2,0 MNOK inntektsgap | N12: 46302
A13: 2 | B13: Sep–okt 2026 | C13: Hvilke drivere forklarer 2027? | D13: Valider SPE60-lag, lønn, vakans, TDI/BOA, EVU og Capex | E13: FS, HR, prosjektportefølje | F13: Controller + fagledelse | G13: Dokumentert driverbok | H13: Drivere godkjent | I13: Krever avstemming | J13: 🔴 | K13: Kilde, eier og beløp per driver | L13: HR, FS og prosjektøkonomi | M13: Avstem lønnsandel 66,8/63,9/64,2 % | N13: 46310
A14: 3 | B14: Okt 2026 | C14: Er enhetsplanene realistiske? | D14: Instituttvise bemannings-, undervisnings- og driftsplaner | E14: Budsjett- og FTE-tabeller | F14: Instituttledere | G14: Fire enhetsbudsjetter | H14: Enhetsleder sign-off | I14: Datagrunnlag klart | J14: 🟢 | K14: Budsjett = bemanning + aktivitet | L14: Godkjente stillingshjemler | M14: Dokumenter lokale forutsetninger | N14: 46318
A15: 4 | B15: Okt–nov 2026 | C15: Tåler planen risiko og scenarioer? | D15: Konsolidering, sensitiviteter, langtidsprognose og reserveanalyse | E15: BUD2027 og tiltak | F15: Senior Controller | G15: Scenario- og risikorapport | H15: Ledelsesgjennomgang | I15: Åpent gap | J15: 🟡 | K15: Resultat, lønnsandel og RAG | L15: Fullført fase 1–3 | M15: Kjør downside på inntekt og BOA | N15: 46332
A16: 5 | B16: Nov–des 2026 | C16: Kan baseline låses? | D16: Kvalitetssikring, styresak, godkjenning og UBW-frys | E16: Budsjettnotat og kontrolliste | F16: Fakultetsdirektør / styret | G16: Godkjent og låst BUD2027 | H16: Formelt vedtak | I16: Ikke klar | J16: 🔴 | K16: Ingen uforklarte differanser | L16: Lukket inntekts- og lønnsgap | M16: Utsett frys til avstemming er signert | N16: 46371
A17: 6 | B17: Jan–des 2027 | C17: Leverer vi mot vedtatt plan? | D17: Månedlig actual vs budget, LE, RAG og tiltak | E17: FactGL, FactAction, Power BI | F17: Controller + enhetsledere | G17: Månedsrapport og revidert LE | H17: Månedlig ledermøte | I17: Planlagt | J17: ⚪ | K17: Avvik, forecast og tiltak | L17: Låst BUD2027 | M17: Etabler rapportkalender M01–M12 | N17: 46397
P18: Rød = uløst avvik | Grønn = avstemt
A20: 2. DRIVERANALYSE OG MODELLAVSTEMMING
A21: Driver | B21: Mekanisme | C21: Kvantifisering | D21: Budsjetteffekt | E21: Risiko | F21: Kontrollaktivitet | G21: Eier | H21: RAG | J21: Avstemming | K21: Modellverdi | L21: Referanse | M21: Differanse | N21: Konklusjon
A22: KD/SPE60 2-års lag | B22: 2025-produksjon styrer 2027-utbetaling | C22: +33 SPE60 × 54 550 kr | D22: +1,80 MNOK inntekt | E22: Lav sats kan gi negativ marginaløkonomi | F22: Avstem FS mot finansieringsgrunnlag | G22: Studiedirektør / Controller | H22: 🟡 | J22: Inntekter | K22: 2.8607e+08 | L22: 288070000 | M22: -2000000.2 | N22: Må avklares før frys
A23: Basisbevilgning | B23: Eksisterende volum ligger i fast basis | C23: 251,8 MNOK konto 3900 | D23: Stabiliserer inntektene | E23: Feil rammeversjon påvirker hele modellen | F23: Signert rammebrev og versjonskontroll | G23: Fakultetsdirektør | H23: 🔴 | J23: Kostnader | K23: 2.82e+08 | L23: 282000000 | M23: 0.12 | N23: Avstemt
A24: Bemanning og vakans | B24: 230 planlagte ÅV med 3,5 % vakans | C24: 221,94 effektive ÅV | D24: Reduserer lønnsbelastning | E24: Tidligere oppstart øker kostnaden | F24: Stillingsregister og månedlig lønnsbro | G24: HR + instituttledere | H24: 🔴 | J24: Netto resultat | K24: 4069999.7 | L24: 6070000 | M24: -2000000.3 | N24: Følger inntektsgapet
A25: BOA/TDI | B25: Frikjøp flytter lønn og gir overhead | C25: T004: 1,80 MNOK; ca. 22 % OH | D25: Bedrer BFV-handlingsrom | E25: Underdekning subsidierer prosjekter | F25: Prosjektkalkyle og dekningsgradsport | G25: Forskningsleder | H25: 🟡 | J25: Lønnsandel, konto | K25: 0.66766875 | L25: 0.645 | M25: 0.022668753 | N25: 2,27 prosentpoeng over mål
A26: EVU/SRS 9 | B26: Inntekt etter fullføringsgrad; tap avsettes straks | C26: T003: 1,40 MNOK | D26: Øker ekstern inntekt | E26: Marginerosjon og tapsavsetning | F26: Kontraktsmargin og månedlig EAC | G26: Instituttleder Ledelse | H26: 🟡 | J26: Effektive ÅV | K26: 221.94 | L26: 230 | M26: -8.06 | N26: Forklares av 3,5 % vakans
A27: Capex / 5 %-regel | B27: Overskudd bindes til investeringer | C27: 32,0 MNOK konto 1250 | D27: Beskytter handlingsrom | E27: Udisponerte reserver kan trekkes inn | F27: Godkjent investeringsplan | G27: Fakultetsdirektør | H27: 🟢
A30: 3. STYRINGSMODELL OG KONTROLLRAMMEVERK
A31: Nivå | B31: Beslutning / ansvar | C31: Frekvens | D31: Input | E31: Kontrollbevis | F31: Eskalering | G31: Output | I31: Kontrollpunkt | J31: Grønn | K31: Gul | L31: Rød | M31: Handling | N31: Rapport
A32: Fakultetsstyret | B32: Godkjenner ramme, resultatmål og investeringsplan | C32: Årlig | D32: Styresak BUD2027 | E32: Vedtaksprotokoll | F32: Uforklart gap eller negativt scenario | G32: Godkjent budsjett | I32: Netto resultat | J32: ≥6,07 MNOK | K32: 0–6,07 MNOK | L32: <0 | M32: Oppdater LE og tiltak | N32: Månedlig
A33: Fakultetsdirektør | B33: Prioriterer bemanning, tiltak og reservebruk | C33: Månedlig | D33: LE, RAG og tiltak | E33: Signert tiltakslogg | F33: Rød status eller >5 % avvik | G33: Ledelsesbeslutning | I33: Lønnsandel | J33: ≤64,5 % | K33: 64,5–67,0 % | L33: >67,0 % | M33: Bemannings- og vakansgjennomgang | N33: Månedlig
A34: Senior Controller | B34: Eier modell, avstemming, konsolidering og forecast | C34: Månedlig | D34: UBW, FS, HR og prosjekt | E34: Avstemmingspakke | F34: Manglende data / versjonsbrudd | G34: Månedsrapport og LE | I34: Budsjettavvik | J34: ≥0 % | K34: 0 til −5 % | L34: <−5 % | M34: Eierforklaring og korrigerende tiltak | N34: Månedlig
A35: Instituttledere | B35: Eier lokale forutsetninger og tiltak | C35: Månedlig | D35: Bemanning, aktivitet og prosjekt | E35: Kommentar og handlingsplan | F35: Gult/rødt enhetsavvik | G35: Oppdatert prognose | I35: Tiltaksgrad | J35: ≥100 % | K35: 75–99,9 % | L35: <75 % | M35: Lukkeplan og eskalering | N35: Ukentlig/månedlig
A36: Prosjekt-/studieledere | B36: Validerer BOA, EVU og studentdrivere | C36: Månedlig/tertial | D36: Prosjekt-EAC og SPE60 | E36: Kalkyle / FS-uttrekk | F36: Negativ margin eller produksjonsfall | G36: Driveroppdatering | I36: BOA/EVU-margin | J36: ≥mål | K36: 0–mål | L36: Negativ | M36: Stopp, reprising eller omfangsendring | N36: Månedlig
I37: Datakvalitet | J37: Ingen gap | K37: Dokumentert midlertidig gap | L37: Uforklart gap | M37: Stopp systemfrys | N37: Ved milepæl
A39: 4. PRIORITERT LUKKEPLAN FØR SYSTEMFRYS
A40: Prioritet | B40: Avvik / risiko | C40: Handling | D40: Eier | E40: Frist | F40: Bevis / ferdigkriterium | G40: Konsekvens hvis ikke lukket | H40: RAG
A41: 1 | B41: 2,0 MNOK manglende inntektslinje | C41: Avstem rammebrev, konto og enhet; korriger kilden eller dokumenter formelt vedtak | D41: Senior Controller / sentral økonomi | E41: 46302 | F41: Modellinntekt = signert ramme | G41: Resultat og styresak blir feil | H41: 🔴
A42: 2 | B42: Lønnsandel 66,8 % mot mål 64,5 % | C42: Avstem konto-basert modell mot FTE-fil og budsjettnotat; dokumenter definisjon og beslutning | D42: Controller / HR | E42: 46310 | F42: Én godkjent lønnsdefinisjon og bro | G42: Feil RAG og svak bemanningsstyring | H42: 🔴
A43: 3 | B43: BOA/TDI-avhengighet | C43: Valider 22 % overhead, finansierte frikjøp og prosjektmargin før stillingsdisponering | D43: Forskningsleder | E43: 46318 | F43: Signerte prosjektkalkyler og frikjøpsplan | G43: BFV subsidierer ekstern aktivitet | H43: 🟡
A44: 4 | B44: EVU/SRS 9-risiko | C44: Krev positiv kontraktsmargin og månedlig EAC før nye leveranser | D44: Instituttleder Ledelse | E44: 46326 | F44: Godkjent kalkyle og tapsrisiko = 0 | G44: Tapsavsetning reduserer resultatet | H44: 🟡
A45: 5 | B45: Formålskapital / 5 %-regel | C45: Knytt overskuddet til vedtatte flerårige investeringer med milepæler | D45: Fakultetsdirektør | E45: 46341 | F45: Godkjent investeringsplan | G45: Risiko for passiv reserve/inndragning | H45: 🟢
A46: 6 | B46: Baseline og sporbarhet | C46: Kjør komplett kontrolliste, godkjenning og lås BUD2027 først etter lukking | D46: Senior Controller | E46: 46371 | F46: Signert kontrollpakke og låst versjon | G46: Ustabil baseline og svakt revisjonsspor | H46: 🔴
A49: SAMLET ANALYSE OG ANBEFALING
A50: Budsjettprosessen er riktig bygget som en driverbasert styringsprosess: ekstern ramme og SPE60-etterslep oversettes til inntekter, bemanning og aktivitet; instituttplanene konsolideres; risiko og langtidsvirkning testes; deretter godkjennes og låses baseline før månedlig oppfølging. Dagens modell er likevel ikke klar for endelig systemfrys. Inntektsrammen er 2,0 MNOK lavere enn dokumentert mål, og konto-basert lønnsandel på 66,8 % avviker fra både målet på 64,5 % og FTE-filens 63,9 %. Anbefalingen er å stoppe ved beslutningsport 5 til disse forholdene er signert avklart. Deretter bør BUD2027 låses sammen med investeringsplan, tiltakseiere og månedlig RAG-rapportering.

Sheet Forecast Methods 2027
A1: PROGNOSEMETODIKK 2027 — FRA BUDSJETT TIL LATEST ESTIMATE
A2: Metodebibliotek for månedlig prognose: Actual YTD + gjenstående estimat (ETC) = helårsprognose (EAC)
A4: SAMLET PLANVOLUM | E4: ACTUAL YTD | I4: ETC | M4: EAC / LE
A5: =SUM(FactBudget_2027[BudsjettBelop]) -> 5.6807e+08 | E5: Bokført hittil | I5: Gjenstående estimat | M5: Actual YTD + ETC
A7: 568,07 MNOK = 286,07 inntekter + 282,00 kostnader | E7: Hentes fra FactGL når 2027-regnskap foreligger | I7: Driverbasert prognose for resterende måneder | M7: Ny forventet helårsverdi
A10: 1. HVORDAN HVER BUDSJETTPOST PROGNOSTISERES
A11: Prioritet | B11: Budsjettpost | C11: Konto / tabell | D11: 2027 baseline | E11: Prognosemetode | F11: Driver / input | G11: Operativ beregning | H11: Oppdatering | I11: Datakilde | J11: Eier | K11: Best case | L11: Base case | M11: Downside | N11: RAG-kontroll
A12: Høy | B12: Basisbevilgning | C12: 3900 | D12: 2.5180015e+08 | E12: Fast ramme + vedtatte endringer | F12: Tildelingsbrev og rammeendringer | G12: Siste godkjente ramme + signerte endringer | H12: Ved rammeendring | I12: KD/UiA rammebrev | J12: Senior Controller | K12: 253800150 | L12: 251800150 | M12: 249800150 | N12: Avvik mot signert ramme
A13: Middels | B13: SPE60-resultatinntekt | C13: FactStudents_2027 | D13: 1800150 | E13: Volum × sats med 2-års lag | F13: Endelig 2025 SPE60-vekst og KD-sats | G13: SPE60-vekst × 54 550 kr | H13: Tertial | I13: FS + KD-sats | J13: Studiedirektør | K13: 2072900 | L13: 1800150 | M13: 1527400 | N13: Avvik >5 % fra godkjent volum
A14: Høy | B14: NFR/EU og TDI | C14: 3400/3420 | D14: 20000000 | E14: Prosjekt-for-prosjekt EAC | F14: Kontrakt, fremdrift, frikjøp og overhead | G14: Bokført inntekt + gjenstående finansiert aktivitet | H14: Månedlig | I14: Prosjektregnskap | J14: Forskningsleder | K14: 22000000 | L14: 20000000 | M14: 17000000 | N14: Negativ margin / OH under mål
A15: Høy | B15: EVU-inntekter | C15: 3600/3630 | D15: 13000000 | E15: Kontraktsbasert EAC | F15: Kontraktsverdi, fullføringsgrad og kostnad til ferdigstillelse | G15: Opptjent inntekt + gjenstående leveranseverdi | H15: Månedlig | I15: EVU-kontrakter | J15: Instituttleder Ledelse | K15: 14500000 | L15: 13000000 | M15: 11000000 | N15: Negativ EAC-margin
A16: Høy | B16: Fast lønn | C16: 5000 | D16: 1.554e+08 | E16: Ansatt-for-ansatt prognose | F16: Årslønn, stillingsprosent, start/slutt og lønnsoppgjør | G16: Bokført lønn + månedslønn × resterende måneder | H16: Månedlig | I16: HR/UBW lønn | J16: HR + instituttledere | K16: 151500000 | L16: 155400000 | M16: 160000000 | N16: Lønnsandel >67 %
A17: Høy | B17: Arbeidsgiveravgift | C17: 5400 | D17: 35600000 | E17: Påslag på prognostisert lønn | F17: Gjeldende AGA-sats og avgiftsgrunnlag | G17: Prognostisert lønnsgrunnlag × AGA-sats | H17: Månedlig | I17: Lønnsprognose | J17: Senior Controller | K17: 34700000 | L17: 35600000 | M17: 36700000 | N17: Avvik følger lønn
A18: Høy | B18: Vakans og rekruttering | C18: FactFTE_2027 | D18: 221.94 | E18: Stilling-for-stilling kapasitetsplan | F18: Faktisk ledighet og forventet tiltredelse | G18: Budsjettert ÅV − vakans frem til realistisk start | H18: Månedlig | I18: HR stillingsregister | J18: HR + instituttledere | K18: 219 | L18: 221.94 | M18: 226 | N18: Vakans lavere enn plan
A19: Middels | B19: Driftskostnader | C19: 6300/6420/6700/7130 | D19: 59000000 | E19: Run-rate + kjente forpliktelser | F19: Faste avtaler, forbruk, pris og engangskostnader | G19: Bokført + åpne PO + normalisert månedsforbruk | H19: Månedlig | I19: UBW / innkjøp | J19: Budsjettansvarlige | K19: 57000000 | L19: 59000000 | M19: 62000000 | N19: Helårsavvik <−5 %
A20: Middels | B20: Investeringer / Capex | C20: 1250 | D20: 32000000 | E20: Milepælsbasert prognose | F20: Kontrakt, anskaffelse, leveranse og aktivering | G20: Bokført + kontraktsfestet beløp per milepæl | H20: Månedlig | I20: Investeringsplan | J20: Fakultetsdirektør | K20: 30000000 | L20: 32000000 | M20: 34000000 | N20: Forsinkelse / ubundet reserve
A21: Høy | B21: Tiltak T001–T004 | C21: FactAction_2027 | D21: 6500000 | E21: Tiltakseier-estimat | F21: Realisert effekt, sannsynlighet og timing | G21: Realisert + sannsynlig gjenstående effekt | H21: Ukentlig/månedlig | I21: FactAction_2027 | J21: Tiltakseiere | K21: 6500000 | L21: 5850000 | M21: 4550000 | N21: Grad <75 %
A22: Beregnet | B22: Netto resultat | C22: Inntekter − kostnader | D22: 4069999.7 | E22: Residualberegning | F22: Alle inntekts- og kostnadsprognoser | G22: Prognostiserte inntekter − prognostiserte kostnader | H22: Månedlig | I22: Samlet modell | J22: Senior Controller | K22: 11372850 | L22: 4069999.7 | M22: -11127250 | N22: <0 rødt; 0–6,07 gult
A25: 2. STANDARD PROGNOSEFORMEL OG MÅNEDSRUTINE
A26: Trinn | B26: Formel / metode | C26: Forklaring | D26: Kontroll | F26: Månedlig aktivitet | G26: Dag 1–3 | H26: Dag 4–5 | I26: Dag 6–7 | J26: Dag 8 | K26: Dag 9 | L26: Dag 10 | M26: Leveranse | N26: Eier
A27: 1 | B27: Actual YTD = bokført M01–cutoff | C27: Låst regnskap hittil i året | D27: Avstem mot hovedbok | F27: Datainnhenting | G27: Lukk periode | H27: HR-uttrekk | I27: FS/prosjekt | M27: Datapakke | N27: Controller
A28: 2 | B28: ETC = prognose for resterende måneder | C28: Bygges fra driverne i tabellen over | D28: Ingen dobbeltelling | F28: Driveroppdatering | H28: Lønn/vakans | I28: BOA/EVU/SPE60 | J28: Drift/Capex | M28: Oppdatert ETC | N28: Eiere
A29: 3 | B29: EAC = Actual YTD + ETC | C29: Ny forventet helårsverdi | D29: Sammenlign med BUD2027 | F29: Analyse | J29: Avviksbro | K29: Scenario | M29: Analysepakke | N29: Controller
A30: 4 | B30: VAC = BUD2027 − EAC | C30: Positivt tall er gunstig for kostnader | D30: Vurder fortegn for inntekter | F30: Beslutning | K30: Ledermøte | M30: Beslutningslogg | N30: Ledelsen
A31: 5 | B31: VAC % = VAC / BUD2027 | C31: Normaliserer vesentligheten | D31: RAG: grønn ≥0; gul 0 til −5 %; rød <−5 % | F31: Publisering | L31: Lås LE | M31: Power BI / rapport | N31: Controller
A32: 6 | B32: Ny LE godkjennes og versjoneres | C32: Bevar forrige prognose for sporbarhet | D32: Dato, eier og kommentar obligatorisk
A35: SLIK BRUKES ARKET
A36: Ved hver månedsavslutning erstattes avsluttede måneder av bokførte tall. For resterende måneder oppdateres driverne — bemanning, kontrakter, prosjektfremdrift, studentproduksjon og investeringer. Summen av bokført hittil og gjenstående estimat blir ny Latest Estimate. Denne sammenlignes med BUD2027, og vesentlige avvik får eier, kommentar og tiltak.

Sheet Model Guide
A1: UiA HHU — Datamodell 2026–2027
A2: Importkontroll, nøkkeltall og oppsett for Power Pivot / Power BI
A4: Kontrollpunkt | B4: Verdi | D4: Modellstatus | E4: Omfang | F4: Merknad | H4: RAPPORTPAKKE
A5: FactBudget 2026 total | B5: =SUM(FactBudget[BudsjettBelop]) -> 130153825 | D5: Importert | E5: 16 kildetabeller | F5: Alle 1 448 datarader fra CSV-settet | H5: Ark | I5: Formål | J5: Hovedsignal
A6: FactGL 2026 LE total | B6: =SUM(FactGL[Belop_signert]) -> 129631567 | D6: Relasjoner dokumentert | E6: 22 relasjoner | F6: 11 kilde-relasjoner + 11 modellkompletteringer | H6: Executive Report | I6: 3-sekunders lederstatus | J6: 2026: +0,52 MNOK mot plan
A7: FactBudget 2027 inntekter | B7: {=SUM(SUMIFS(FactBudget_2027[BudsjettBelop],FactBudget_2027[Konto],{"3900","3670","3600","3630","3400","3420"}))} -> 2.8607e+08 | D7: DAX validert | E7: 36 mål | F7: Korrigert mot faktiske kolonnenavn | H7: Unit Analysis | I7: 300-sekunders detaljanalyse | J7: Rettsvitenskap +1,15 / Økonomi −0,71 MNOK
A8: FactBudget 2027 kostnader | B8: =SUM(FactBudget_2027[BudsjettBelop])-B7 -> 2.82e+08 | D8: Datamodellhandling | E8: Manuell sluttføring | F8: Legg Excel-tabellene i Data Model og opprett målene fra DAX Measures | H8: 2027 Plan Report | I8: Fremoverskuende beslutningsstøtte | J8: 4,07 MNOK resultat; 2,0 MNOK inntektsgap
A9: FactBudget 2027 netto resultat | B9: =B7-B8 -> 4069999.7
A12: Viktig datakvalitetsfunn | B12: CSV-verdi | C12: Dokumentert verdi | D12: Differanse | E12: Konsekvens | F12: Anbefaling
A13: BUD2027 inntekter | B13: 2.8607e+08 | C13: 288070000 | D13: -2000000.2 | E13: Netto blir 4,07 MNOK, ikke 6,07 MNOK | F13: Avklar manglende 2,0 MNOK inntektslinje før publisering
A16: Tabell | B16: Datarader | C16: Status
A17: DimAccountHierarchy | B17: 20 | C17: Importert
A18: DimDate | B18: 12 | C18: Importert
A19: DimDate_2027 | B19: 12 | C19: Importert
A20: DimForecastVersion | B20: 5 | C20: Importert
A21: DimOrganization | B21: 4 | C21: Importert
A22: FactAction | B22: 4 | C22: Importert
A23: FactAction_2027 | B23: 4 | C23: Importert
A24: FactBudget | B24: 432 | C24: Importert
A25: FactBudget_2027 | B25: 384 | C25: Importert
A26: FactEVM | B26: 12 | C26: Importert
A27: FactFTE | B27: 48 | C27: Importert
A28: FactFTE_2027 | B28: 48 | C28: Importert
... A32: Relationships | B32: 22 | C32: Importert

Sheet gr_data
A1: Grunnlagsdataene for Budsjett 2027, det tilhørende settet med DAX-målekoder og en grundig forklaring av prognosemodellene for Handelshøyskolen ved UiA (HHU) er nå klargjort og publisert som CSV-filer i Studio-panelet.
A4: 1. Genererte Grunnlagsdata for Budsjett 2027 (CSV-filer i Studio)
A5: De nye CSV-filene er strukturert for direkte import i Power BI Desktop (semi-kolon ; skilletegn, UTF-8 med BOM):
A7: FactBudget_2027.csv: Periodisert årsbudsjett for alle 12 måneder i 2027. Reflekterer HHUs samlede ramme på 288,07 MNOK i inntekter og 282,00 MNOK i kostnader, som gir et planlagt driftsüberskudd på +6,07 MNOK (baseline BAC +4,80 MNOK), fordelt på kontoplan DFØ R-102 og HHUs 4 budsjettansvarsområder.
A8: FactFTE_2027.csv: Bemannings- og årsverksplan for 2027. HHU disponerer 230 årsverk (155 UF og 75 TA fordelt på 252 ansatte), med en innlagt sentral 3,5 % vakansfaktor i UBW Planlegger for å ta høyde for naturlig rekrutteringstid (3–6 måneder).
A9: FactStudents_2027.csv: Utdannings- og studiepoengmodell for 2027. Dokumenterer 3 450 registrerte studenter og 3 153 SPE60 (hvor 33 SPE60 utgjør resultatvekst fra 2025-produksjonen utbetalt i Kategori 1 @ 54 550 kr/SPE60).
A10: FactAction_2027.csv: Omstillingstiltak T001_2027–T004_2027 (frys i administrativ rekruttering, faglig reallokering til Siviløkonom, lansering av EVU Master i HR, samt økt TDI research buy-out).
A11: DimDate_2027.csv, DimOrganization.csv, DimAccountHierarchy.csv, DimForecastVersion.csv: Dimensjonstabeller for 2027.
A15: 2. Komplett sett med DAX-målekoder for Budsjett 2027
A16: DAX-målekodene legges inn i Power BI i dedikerte Display Folders:
A18: // ===============================================================================
A19: // FOLDER 1: BUDSJETT 2027 BASELINE (_01 Budsjett 2027 BAC)
... A148: Tallstørrelse: I henhold til Rundskriv F-05-20 må ubrukte avsetninger utover 5 % av årets bevilgning være formelt bundet til Universitetsstyrets godkjente investeringsplaner (IT-fornyelse, laboratorier, AACSB-revisjon) for å forhindre statlig

Sheet bud2026
A1: 5
A2: Datatsettet, datamodell-diagrammet og relasjonstabellen er nå publisert i Studio-panelet som 11 CSV-filer og én HD-diagramfil (powerbi_datamodel_hhu_2026_diagram.png).
A5: 1. Fordeling på Budsjettansvarsområder (HHU 2026)
A6: I henhold til UiA sin organisasjonsstruktur og kontoplan3more_horiz er årsbudsjettet på 130 153 825 kr fordelt på HHUs fire primære budsjettansvarsområder (koststeder/enheter):
A7: Koststed / OrgKode | B7: Budsjettansvarsområde / Enhet | C7: Ansvarlig Leder | D7: Vedtatt Årsbudsjett 2026 (NOK) | E7: Andel % | F7: Sentrale Faglige og Operative Ansvarsområder
A8: K10000 | B8: HHU Fakultetsadministrasjon & Felles | C8: Fakultetsdirektør Kristian Jørgensen6 | D8: 14 000 000 kr | E8: 10,8 % | F8: AACSB re-akkreditering7, fellesinfrastruktur, IT-lisenser og overordnet fakultetsstyring6.
A9: K11000 | B9: Institutt for ledelse og innovasjon | C9: Instituttleder Ledelse4 | D9: 38 500 000 kr | E9: 29,6 % | F9: Master i org. og ledelse, bachelor i markedsføring, oppdragsutdanning (EVU)8.
A10: K12000 | B10: Institutt for rettsvitenskap | C10: Instituttleder Ole Dag Rike46 | D10: 29 250 000 kr | E10: 22,5 % | F10: Master og bachelor i rettsvitenskap (jus), lovpålagte emner for siviløkonomer9.
A11: K13000 | B11: Institutt for økonomi | C11: Instituttleder Økonomi4 | D11: 48 403 825 kr | E11: 37,2 % | F11: Siviløkonomstudiet (M-SIVØK), Bachelor i øk.ad, ph.d.-utdanning og NFR/EU-forskning3more_horiz.
A12: SUM HHU | B12: HANDELSHØYSKOLEN TOTAT | C12: Dekan Kristin Wallevik6 | D12: 130 153 825 kr | E12: 100,0 % | F12: Vedtatt totalramme for HHU i Universitetsstyret25.
A15: 2. Utfordringer i Datasetter knyttet til Budsjettansvarsområde (2026)
A16: Datamaterialet i FactGL.csv, FactFTE.csv og FactAction.csv er konstruert for å belyse fire klassiske styrings- og avviksutfordringer i matrisen mellom linjeansvar (instituttleder) og prosjektansvar (prosjektleder/studieprogramleder)11more_horiz:
A18: 1. Bemanningsavvik og vakansstyring (K13000 Inst. for økonomi):
A19: Utfordring: Instituttet har lav vakansrate fordi to nye førsteamanuenser startet tre måneder tidligere enn forutsatt i UBW-planleggeren.
A20: Effekt i data: Påløpte lønnskostnader YTD per 30. september viser et merforbruk på +3,5 % mot periodisert budsjett.
A21: 2. Kompenserende vakanshold (K12000 Inst. for rettsvitenskap):
A22: Utfordring: For å avlaste fakultetets samlede ramme holdes en professorhjemmel midlertidig ubesatt i Q2–Q3 (Tiltak T004_HHU).
A23: Effekt i data: Gir et akkumulert mindreforbruk på -800 000 kr i FactGL.csv og FactAction.csv.
A24: 3. SRS 9 Tapsavsetning på oppdragsutdanning (K11000 Inst. for ledelse):
A25: Utfordring: På oppdragsprosjektet EVU001 har timelærerforbruket overskredet kontraktsrammen. I henhold til SRS 9 kreves det umiddelbar inntektsføring etter fullføringsgrad og tapsavsetning14.
A26: Effekt i data: Postering på 350 000 kr på konto 7790 (Avsetning for forventet tap) i M09.
A27: 4. AACSB Akkrediteringskostnader vs. TDI Overhead (K10000 Admin):
... A246: 💡 Alt ligger klart i Studio-panelet ditt for videre analyse!

Sheet bud2027
A1: De nye strategiske midlene, regional støtte og studieplasstildelingene påvirker 2027-budsjettet ved Universitetet i Agder (UiA) gjennom tre hovedmekanismer: KDs resultatfinansiering med to års etterslep, indirekte kostnadsdekning (overhead) fra ekstern forskning (BOA), og rammebetingelsene for formålskapital og avsetninger (Note 15 og F-05-20).
A4: 1. Resultatbevilgning via KDs toårige etterslep
A6: Studiepoengproduksjon (SPE60): Tildelingen av nye studieplasser (blant annet 30 studieplasser til profesjonsstudiet i psykologi1, 10 studieplasser i IKT2 og arbeidsplassbasert barnehagelærerutdanning12) øker studentmassen og studiepoengproduksjonen i 2025 og 2026.
A7: Inntektseffekt i 2027: Under Kunnskapsdepartementets (KD) finansieringsmodell utbetales resultatbasert uttelling for avlagte studiepoeng med to års etterslep3more_horiz. Studiepoeng produsert av disse studentkullene i 2025 vil dermed gi direkte økt resultatbevilgning på statsbudsjettet for 2027 ut fra KDs tre finansieringskategorier (Kategori 1: 54 550 kr; Kategori 2: 81 800 kr; Kategori 3: 190 900 kr per 60 SPE)67.
A11: 2. Ekstern forskningsfinansiering og TDI-overhead (BOA)
A13: Regionale fond og stiftelser: Betydelige eksterne tilsagn – slik som Sør-fondets 30 mill. kr (hvorav 18 mill. kr går til nevrovitenskap)8, Sørlandets kompetansefonds 18 mill. kr over tre år8 og Aust-Agder utviklings- og kompetansefond8 – utvider UiAs eksternt finansierte prosjektportefølje (Bidrags- og oppdragsaktivitet / BOA).
A14: Periodisering etter SRS 10: I henhold til SRS 10 inntektsføres disse bidragsmidlene i 2027-budsjettet i eksakt takt med at prosjektkostnadene påløper (motsatt sammenstilling)9.
A15: Avlastning av basisrammen (TDI-modellen): Gjennom TDI-modellen (Totalkostnadsmodellen) dekker eksternt finansierte prosjekter sine egne direkte kostnader pluss et påslag for indirekte felleskostnader (overhead) til husleie, IT, bibliotek og administrasjon9more_horiz. Denne overhead-refusjonen overføres tilbake til fakultetene og fellestjenestene i 2027, noe som direkte avlaster universitetets faste basisbevilgning1011.
A19: 3. Engangssatsinger, investeringer og avsetningsreglementet (Note 15 & F-05-20)
A21: Strategiske engangsmidler: Løyvinger til KI og ny teknologi (over 18 mill. kr, hvorav 15 mill. kr til felles infrastruktur og 500 000 kr per fakultet)1213, fleksibel utdanning (6 mill. kr sentralt + 500 000 kr per fakultet)14 og Vitensenteret Kristiansand UiA (5 mill. kr til inventar/utstyr)14 utgjør tidsavgrensede eller engangsbaserte tildelinger.
A22: Binding i Note 15: Universitetets samlede avsetninger i Note 15 økte til 295,4 mill. kr per 31.12.20251516. Av dette er hele 257 mill. kr formelt avsatt til universitetsstyrets godkjente investeringsplan for 2026–2028 (som dekker campusutvikling, spesialarealer for psykologiutdanningen og Vitensenteret)15more_horiz.
A23: Kontroll mot F-05-20 (5 %-regelen): Ved å binde 13 % av bevilgningen til vedtatte investeringer, holdes UiAs frie avsetninger til andre formål på ca. 2 %1718. Dette sikrer at universitetet overholder KDs retningslinjer i Rundskriv F-05-20, samtidig som engangsmidler forhindres fra å skape udekket overbemanning eller faste driftsforpliktelser i 20271019.
... A43: Tabellen viser overgangen fra 2026-baseline12 til 2027-budsjett for HHU, spesifisert per inntektsstrøm, regnskapsprinsipp og kilde:
A44: Inntektskomponent | B44: 2026 Baseline (MNOK)1 | C44: Endring / Nye midler (NOK) | D44: 2027 Prognose (MNOK) | E44: Beregningsgrunnlag og Regnskapsregel
A45: Statlig grunnbevilgning (Basis) | B45: 246,80 | C45: +5 200 000 kr | D45: 252,00 | E45: Lønns- og prisjustering (~2,1 %) på den faste basisrammen34.
A46: KDs resultatbevilgning (SPE60) | B46: 0,00 (bakt i basis) | C46: +1 800 150 kr | D46: 1,80 | E46: 2-års etterslep: Marginalsats for Kategori 1 (54 550 kr/SPE60)56 for økt studiepoengproduksjon i 2025 (+33 SPE60).
A47: Strategiske engangsmidler (KI) | B47: 0,00 | C47: +500 000 kr | D47: 0,50 | E47: Styretildeling til hvert fakultet for implementering av KI og ny teknologi78.
A48: Strategiske midler (Fleksibilitet) | B48: 0,00 | C48: +500 000 kr | D48: 0,50 | E48: Styretildeling til hvert fakultet for fleksibilisering av studietilbud8.
A49: Øremerket støtte (AACSB) | B49: 0,2789 | C49: +0 kr (videreføres) | D49: 0,27 | E49: Særskilt tildeling fra Universitetsstyret til arbeidet med re-akkreditering89.
A50: Ekstern forskning (BOA - Bidrag) | B50: 18201 | C50: +1 800 000 kr | D50: 20,00 | E50: SRS 10 (Motsatt sammenstilling): Økt NFR/EU-frikjøp610. Inkluderer TDI-overhead910.
A51: Oppdrag & EVU (Studieavgifter) | B51: 11601 | C51: +1 400 000 kr | D51: 13,00 | E51: SRS 9 (Fullføringsgrad): Økning i markedsfinansierte videreutdanninger (f.eks. Master i HR og ledelse)1112.
A52: SAMLEDE INNTEKTER (HHU) | B52: 276,87 MNOK | C52: +11 200 150 kr | D52: 288,07 MNOK | E52: Samlet inntektsvekst på +4,0 % for HHU.
A55: 2. Regneeksempel for de tre viktigste inntektsdriverne
A56: A. KDs resultatbaserte uttelling (SPE60 i Kategori 1 med 2-års etterslep)
A57: HHUs studier (økonomi, ledelse, juss) er plassert i KDs Kategori 1, der insentivsatsen utgjør 54 550 kr per 60 avlagte studiepoeng (1 SPE60)56.
A58: Dersom HHU øker studentenes studiepoengproduksjon i 2025 med totalt 1 980 studiepoeng (tilsvarende +33 helårsstudenter / SPE60), utløser dette følgende inntektsvekst i 2027-budsjettet5:
A59: $$\text{Inntektseffekt i 2027} = 33 \text{ SPE60} \times 54\,550 \text{ kr/SPE60} = \mathbf{1\,800\,150 \text{ kr}} \quad (\mathbf{+1,80 \text{ MNOK}})$$
A60: Merk: Nettobudsjetteringsprinsippet gjør at eksisterende studievolum ligger fast i basis, så Kategori 1-satsen gjelder kun for marginale volumendringer56.
A63: B. Strategiske tildelinger fra Universitetsstyret
A64: I henhold til vedtak i Universitetsstyret tilføres HHU tre spesifikke strategiske tildelinger7more_horiz:
A66: 1. KI og ny teknologi: 500 000 kr direkte til fakultetets arbeid med KI i undervisning og forskning78.
A67: 2. Fleksible utdanningstilbud: 500 000 kr direkte til utvikling av nett- og samlingsbaserte tilbud8.
A68: 3. AACSB Re-akkreditering: 265 000 kr øremerket revisjon og internasjonalt kvalitetssikringsarbeid89.
A70: $$\text{Sum strategiske engangsmidler} = 500\,000 \text{ kr} + 500\,000 \text{ kr} + 265\,000 \text{ kr} = \mathbf{1\,265\,000 \text{ kr}} \quad (\mathbf{1,27 \text{ MNOK}})$$
... A86: Veksten drives av en kombinasjon av kr 1,8 MNOK i resultatvekst fra økt studiepoengproduksjon i Kategori 156, kr 1,27 MNOK i øremerkede strategiske midler til KI, fleksibilitet og AACSB7more_horiz, samt kr 3,2 MNOK i økt ekstern prosjektomsetning (BOA) gjennom frikjøp og studieavgifter1012.

Sheet org_data
A1: Use Case: Seniorrådgiver / Senior Controller ved Handelshøyskolen (HHU) – Universitetet i Agder
A4: 1. Stillingsprofil & Strategisk Kontekst
A5: Handelshøyskolen ved UiA (HHU) er internasjonalt AACSB-akkreditert, organisert i tre institutter (Ledelse og innovasjon, Rettsvitenskap, Økonomi) samt fakultetsadministrasjonen, med Hovedarbeidssted på Campus Kristiansand. Fakultetet håndterer om lag 3 450 registrerte studenter (3 120 SPE60-ekvivalenter), 230 årsverk (155 faglige UF-årsverk og 75 teknisk-administrative TA-årsverk) og en samlet helårsramme i 2026 på 276,6 MNOK i inntekter mot 274,4 MNOK i kostnader (netto avvik/overskudd: +2,2 MNOK).
A6: Stillingen som Seniorrådgiver / Senior Controller (stillingskode 1364) inngår i fakultetets økonomiteam i fakultetsadministrasjonen, rapporterer direkte til fakultetsdirektøren, og leverer strategisk beslutningsstøtte til dekan, instituttledere og sentral økonomiavdeling.
A8: +----------------------------------------------------------------------------------------------------+
A9: | ORGANISATORISK PLASSERING OG RAPPORTERINGSLINJE |
A10: +----------------------------------------------------------------------------------------------------+
A11: | Universitetsdirektør / Sentral Økonomiavdeling <---> Dekan & Fakultetsstyre ved HHU |
A12: | │ |
A13: | Fakultetsdirektør |
A14: | │ |
A15: | Seniorrådgiver / Senior Controller (Kode 1364) |
... A121: 5. Leveranser og Suksesskriterier for Seniorrådgiveren
A122: Område | B122: Mål og Kvalitetskrav | C122: Evaluering & Dokumentasjon
A123: Kvalitetssikring av Budsjett | B123: Konsolidere HHUs årsbudsjett i UBW Planlegger med korrekte sosiale kostnader, realistisk vakansfaktor og avstemt studiepoengprognose. | C123: Sjekkliste for systemfrys i Q4 fullført uten avvik.
A124: BOA- og TDI-oppfølging | B124: Sikre 100 % korrekt periodisering etter SRS 10 for NFR/EU-bidrag og full overhead-dekning på oppdragskontrakter. | C124: Null uidentifiserte avsetningstap ved tertialavslutning.
A125: Beslutningsstøtte til Dekan | B125: Utarbeide tertialvise månedsrapporter med "So What?"-analyse, RAG-status og 2–3 konkrete handlingsalternativer ved avvik. | C125: Presentert for dekan og instituttledere i dialogmøter.
A126: Power BI Cockpit | B126: Opprettholde rollestyrt tilgang (RLS) på fakultets- og instituttnivå, og sikre oppdaterte Power BI-dashbord i tråd med 3-30-300-regelen og Tufte-

Sheet meta_data
A1: complete, realistic CSV dataset, along with two technical architecture diagrams tailored specifically to the Handelshøyskolen ved UiA (HHU) financial and operational ecosystem for the 2026 budget year (with Actuals as of September 30, 2026 / M01–M09 and Q4 Forecast / M10–M12).
A2: All 11 CSV files and both high-resolution diagram images have been generated and published to your Studio panel.
A5: 1. Overview of Generated CSV Dataset (Published to Studio)
A6: The dataset is formatted with semi-colon (;) delimiters and UTF-8 BOM encoding for direct import into Power BI Desktop or Excel [1, 2].
A7: CSV Filename | B7: Table Type | C7: Key Contents & HHU-Specific Specifics
A8: FactGL.csv | B8: Fact Table | C8: Monthly general ledger entries [1]. Contains Actuals (M01–M09) and Forecast Q4 (M10–M12) [1]. Includes HHU transactions for AACSB accreditation audits (Konto 6700 / Project AACSB01), EVU001 contract loss provisions (Konto 7790 / SRS 9) [1], and NFR research buy-out (Konto 3400/5000 / SRS 10) [1].
A9: FactBudget.csv | B9: Fact Table | C9: Approved 2026 annual budget (BUD2026) periodized by month, department, and account line [1, 3].
A10: FactFTE.csv | B10: Fact Table | C10: Monthly staffing tracking [1]. For HHU: 155 UF FTEs (vitenskapelige) [2], 75 TA FTEs (teknisk-administrative) [2], 252 staff members, vacancy counts, and monthly salary expenses [1].
A11: FactStudents.csv | B11: Fact Table | C11: Student metrics and credit production [1]. Tracks HHU’s 3,450 registered students, 3,120 SPE60 (helårsstudenter), KD Category 1 rates (54,550 NOK/60 SPE), and student-to-faculty ratio (22.3 students/UF) [2, 4].
A12: FactEVM.csv | B12: Fact Table | C12: Earned Value parameters per month [1, 5]. BAC = 1,433.0 MNOK, EAC = 1,444.0 MNOK, ETC = 100.0 MNOK [2, 5], CPI = 0.95, SPI = 0.92, VAC = -11.0 MNOK [2, 5].
A13: FactAction.csv | B13: Fact Table | C13: Restructuring action tracker [1]. Includes HHU administrative vacancy freeze (T001), academic reallocation (T002), and EVU portfolio expansion (T003) [2, 6].
A14: DimOrganization.csv | B14: Dimension | C14: Hierarchical organization structure [1]. Level 1: UiA [2]; Level 2: HHU, TEK, HEL, SAM, HUM, ADM [2]; Level 3 (HHU): Institutt for ledelse og innovasjon (I001), Institutt for rettsvitenskap (I002), Institutt for økonomi (I003), HHU Fakultetsadministrasjon (I004).
A15: DimAccountHierarchy.csv | B15: Dimension | C15: DFØ R-102 standard chart of accounts hierarchy for state accrual accounting (SRS) [1, 7].
A16: DimDate.csv | B16: Dimension | C16: 2026 calendar dimension marking M01–M09 as Actual (ErActualYTD = TRUE) and M10–M12 as Forecast [1, 3].
A17: DimForecastVersion.csv | B17: Dimension | C17: Version metadata (BUD2026, ACTUAL_YTD_SEP2026, FC_Q4_2026, LE_2026) [1, 3].
A18: Relationships.csv | B18: Documentation | C18: Cardinality and cross-filtering rules ($1:*$ single direction) for setting up the Power BI semantic model [1].
A21: 2. Specific HHU Issues Represented in the Data
A23: 1. KD 2025 Category 1 Funding Bottleneck: HHU produces 3,120 SPE60 across its three institutes (Ledelse og innovasjon, Rettsvitenskap, Økonomi) [2]. Because business/law studies fall under KD Category 1 (54,550 NOK per 60 SPE) [4] and HHU operates at 22.3 students per UF FTE [2], marginal volume expansion does not cover clinical/seminar teaching costs [4].
A24: 2. AACSB Accreditation Costs: Account 6700 and Project AACSB01 capture 450,000 NOK in international review audit fees and consultant support in M03 and M09 to maintain HHU's international accreditation.
A25: 3. SRS 9 Contract Loss Provision (EVU001): Account 7790 records a 350,000 NOK loss provision in M09 for project EVU001 (custom corporate executive program) due to delivery overruns, complying with SRS 9 onerous contract rules [1].
A26: 4. SRS 10 NFR Research Buy-out (Frikjøp): Accounts 3400 and 5000 on project NFR001 reflect research buy-out where external grant revenue matches project expenses [1, 8].
A27: 5. Positive Net Surplus (+2.2 MNOK): HHU delivers total revenues of 276.6 MNOK against expenses of 274.4 MNOK, contributing +2.2 MNOK in positive operating margin to offset central deficits [2].
A31: 3. Data Workflow Diagram: Ingestion, ETL & Reporting
A32: The visual image data_workflow_ingestion_reporting.png is published in Studio. Below is the workflow breakdown:
A34: +---------------------------------------------------------------------------------------------------+
A35: | UiA DATA INGESTION & REPORTING PIPELINE WORKFLOW |
A36: +---------------------------------------------------------------------------------------------------+
A38: [ PHASE 1: SOURCE LAYER (Kildesystemer) ]
... A93: | [Studenter, SPE] | | EAC, CPI, SPI] | | Ansvarlig] |

Sheet bud_prosess
A1: Use Case: 2027 Budgeting & Financial Planning for Handelshøyskolen ved UiA (HHU)
A4: 1. Strategic Context & Organizational Framework
A5: Handelshøyskolen ved UiA (HHU) is an internationally AACSB-accredited business school at the University of Agder, organized into three academic departments (Institutt for ledelse og innovasjon, Institutt for rettsvitenskap, and Institutt for økonomi) plus the faculty administration on Campus Kristiansand.
A6: HHU operates with a 2026 baseline of 3,450 registered students (3,120 SPE60 credit-equivalents), 230 FTEs (155 academic/UF FTEs and 75 technical-administrative/TA FTEs), and a total annual operating budget of 276.6 MNOK in revenue against 274.4 MNOK in total expenses, yielding a net operating surplus of +2.2 MNOK.
A7: In accordance with the UiA Controller Framework and the position profile for Senior Controller / Seniorrådgiver (stillingskode 1364), the senior controller leads the 2027 budgeting cycle. The controller reports to the Faculty Director (Fakultetsdirektør) and works closely with the Dean (Dekan), Department Heads (Instituttledere), and the central University Financial Department (Sentral Økonomiavdeling) to prepare a realistic, driver-based 2027 budget (BUD2027) and 5-year long-term forecast (PROG2027–2031) in Unit4 UBW Planlegger.
A9: +----------------------------------------------------------------------------------------------------+
A10: | HHU 2027 BUDGET PLANNING & GOVERNANCE HIERARCHY |
A11: +----------------------------------------------------------------------------------------------------+
A12: | KD Award Letter (Tildelingsbrev Kap. 260) ──> UiA Board Allocation Frame |
A13: | │ |
A14: | Fakultetsdirektør |
A15: | │ |
... A76: Based on the 2026 baseline (276.6 MNOK Revenue / 274.4 MNOK Expenses), the table below presents the full 2027 budget reconciliation model (BUD2027) prepared by the Senior Controller:
A77: Budget Line Item | B77: Account Class / Source | C77: 2026 Baseline (MNOK) | D77: 2027 Adjustments / Drivers | E77: 2027 Budget (MNOK) | F77: Notes & Regulatory Justification
A78: KD State Allocation (Basis) | B78: Konto 3900 / Post 50 | C78: 246.8 | D78: +5.2 (Price/salary indexation ~2.1%) | E78: 252.0 | F78: Fixed basis protected by net budgeting.
A79: KD Performance (2025 SPE60 Lag) | B79: Konto 3900 / FS | C79: 0 | D79: +1.8 (+33 SPE60 @ Kat 1 54 550 kr) | E79: 1.8 | F79: 2-year lag payout from 2025 credit growth.
A80: Research Grants (NFR / EU) | B80: Konto 3400 / 3420 | C80: 18.2 | D80: +1.8 (Increased buy-out / TDI overhead) | E80: 20.0 | F80: SRS 10 revenue matching project expenses.
A81: Commission & EVU Revenue | B81: Konto 3600 / 3630 | C81: 11.6 | D81: +1.4 (Expanded corporate EVU portfolio) | E81: 13.0 | F81: SRS 9 completion-rate accounting (T003 target).
A82: TOTAL REVENUE (BUD2027) | B82: Klasse 3 | C82: 276.6 | D82: +10.2 MNOK (+3.7%) | E82: 286.8 | F82: Approved 2027 Revenue Baseline (BAC).
A83: Personnel Expenses (Lønn) | B83: Konto 5000–5999 | C83: 179.4 | D83: +4.6 (Lønnssoppgjør minus T001/T002 freeze) | E83: 184.0 | F83: Keeps labor share at 64.2% of revenue (<65.0% norm).
A84: Operating Expenses (Drift) | B84: Konto 6000–7999 | C84: 64.6 | D84: +1.4 (IT licenses, travel, AACSB audit) | E84: 66.0 | F84: Includes AACSB review fees (Konto 6700).
A85: Capital Expenditures (Capex) | B85: SRS 17 / Konto 1250 | C85: 30.4 | D85: +1.6 (IT infrastructure & lab renewal) | E85: 32.0 | F85: Approved multi-year investment plan.
A86: TOTAL EXPENSES (BUD2027) | B86: Klasse 5–7 | C86: 274.4 | D86: +7.6 MNOK (+2.8%) | E86: 282.0 | F86: Approved 2027 Expense Baseline (EAC).
A87: NET OPERATING RESULT | B87: Net Margin | C87: 2.2 | D87: +2.6 MNOK Net Surplus | E87: +4.8 | F87: Positive operating contribution to UiA reserves.
A90: 5. Power BI 2027 Budgeting Measures & RAG Status
A91: To monitor 2027 execution against the BUD2027 baseline in Power BI, the Senior Controller uses these DAX measures:
A93: // 1. Approved 2027 Budget Baseline (BAC)
A94: HHU 2027 Budget BAC =
A95: CALCULATE(
A96: SUM('FactBudget'[BudsjettBelop]),
A97: 'DimOrganization'[Fakultetsnavn] = "Handelshøyskolen ved UiA (HHU)",
A98: 'DimForecastVersion'[VersjonKode] = "BUD2027"
A99: )
A101: // 2. 2027 YTD Budget Variance (Actual vs BUD2027)
A102: HHU 2027 Budget Variance YTD =
A103: VAR ActualYTD = CALCULATE([Actual YTD], 'DimOrganization'[Fakultetsnavn] = "Handelshøyskolen ved UiA (HHU)")
... A134: [x] System Freeze Execution: Locked BUD2027 in Unit4 UBW prior to final board approval to establish an immutable baseline for 2027 variance tracking.

Sheet bud_prosess2
A1: Budsjettnotat 2027: Handelshøyskolen ved UiA (HHU)
A2: Til: Fakultetsstyret ved Handelshøyskolen ved UiA Fra: Fakultetsadministrasjonen Dato: 15. oktober 2026 Saksbehandler: Seniorrådgiver innen strategisk økonomistyring Gjelder: Forslag til budsjettramme for 2027
A5: 1. Executive Summary og Vedtaksforslag
A6: Budsjettet for 2027 markerer fullføringen av overgangen til Kunnskapsdepartementets (KD) nye finansieringsregime. For Handelshøyskolen ved UiA (HHU) er dette budsjettet det viktigste verktøyet for å opprettholde faglig autonomi og vår internasjonale posisjon gjennom AACSB-akkrediteringen. Strategien for 2027 er todelt: Vi skal utnytte handlingsrommet i Bevilgningsfinansiert virksomhet (BFV) for å beskytte kjerneaktiviteten, samtidig som vi profesjonaliserer prosjektøkonomien for å sikre vekst gjennom eksternfinansiering (BOA).
A7: Hovedmåltallet for 2027 viser et planlagt driftsoverskudd som skal anvendes til strategiske investeringer fremfor passiv sparing:
A8: Kategori | B8: Budsjettert 2027 (MNOK)
A9: Samlede inntekter | B9: 286,8
A10: Samlede kostnader | B10: 282,0
A11: Forventet driftsresultat | B11: +4,8
A12: Vedtaksforslag
A14: Fakultetsstyret godkjenner budsjettrammen for 2027 med en samlet inntektsramme på 286,8 MNOK og kostnadsramme på 282,0 MNOK.
A15: Fakultetsdirektøren gis mandat til å realisere omstillingstiltakene T001–T004 for å sikre budsjettbalanse og faglig handlingsrom.
A16: Fakultetsledelsen gis fullmakt til å utarbeide periodiserte investeringsplaner (Capex) for å styre overskuddet i tråd med 5 %-regelen.
A17: Budsjettoppfølgingen skal skje i henhold til 3-30-300-regelen med månedlig rapportering av RAG-status i Power BI.
A19: Det økonomiske handlingsrommet i 2027 er direkte avhengig av vår evne til å navigere i de nye statlige rammebetingelsene.
A20: 2. Rammebetingelser og KDs Finansieringsmodell 2027
A21: Overgangen til KDs 2025/2027-modell innebærer et skifte mot "styring i det store", der departementet overlater dimensjoneringsrisikoen i sin helhet til fakultetet.
A22: Strategisk analyse av finansieringslogikken:
A24: Nettobudsjetteringseffekten: Eksisterende studieplassvolum ligger fast i basisbevilgningen, som fungerer som et beskyttende "skjold" mot devalueringsrisiko. Det er kritisk å forstå at basisbevilgningen dekker våre reelle historiske kostnader, mens nye tildelinger og produksjonsendringer følger de nye satsene.
A25: Kategori 1-satser (54 550 kr per 60 SPE): Våre kjernefag innen økonomi, ledelse og juss er plassert i laveste kategori. Denne satsen reflekterer et insentiv for endring, ikke den reelle kostnaden ved utdanning av høy kvalitet. Å skalere opp volum utelukkende basert på denne satsen vil skape et strukturelt underskudd på sikt.
A26: 2-års etterslep på SPE60: Inntektene i 2027 er låst til produksjonen i 2025. Dette krever at vi i dag styrer gjennomføringsgraden for 3 120 SPE60-ekvivalenter for å sikre inntektsstrømmen i 2029.
... A78: Oppsummering: Budsjett 2027 ruster Handelshøyskolen ved UiA for fremtiden. Ved å kombinere streng kostnadskontroll med offensive investeringer og profesjonalisert prosjektøkonomi, sikrer vi HHUs posisjon som et autonomt og internasjonalt anerkjent fakultet.

Sheet bud_metoder
A1: I offentlig sektor og universitets- og høgskolesektoren (UH) har budsjettering beveget seg fra passiv historisk rammetildeling til strategisk virksomhetsstyring. Nedenfor gis en gjennomgang av de mest sentrale budsjetteringsmetodene, følges opp av en konkret anbefaling for Handelshøyskolen ved UiA (HHU).
A4: 1. Oversikt over ulike budsjetteringsmetoder
A5: A. Historisk / Inkrementell budsjettering (Rammebudsjettering)
A7: Konsept: Fjorårets budsjett eller regnskap legges til grunn som baseline, og justeres marginalt opp eller ned basert på generell pris- og lønnsvekst (deflator) samt flate rammekutt (f.eks. ABE-kutt).
A8: Fordeler: Enkel å gjennomføre, krever lite ressursbruk.
A9: Ulemper: Konserverer historiske skjevheter, skjermer ineffektive aktiviteter og fanger i liten grad opp reelle endringer i studieproduksjon eller bemanningsstruktur.
A11: B. Driverbasert budsjettering (Driver-Based Budgeting)
A13: Konsept: Budsjettet bygges opp fra underliggende operasjonelle volum- og aktivitetsdrivere.
A14: Inntektssiden styres av KDs finansieringsmodell (antall avlagte studiepoeng/SPE60, kandidater og PhD-er).
A15: Kostnadssiden styres av antall årsverk (UF/TA), lønnstrinn, sosiale kostnader, antall emner og undervisningstimer.
A16: Fordeler: Høy presisjon, direkte kobling mellom faglig aktivitet og økonomisk konsekvens, og mulighet for årsakssammenhengende avviksanalyser (volum- vs. prisavvik).
A17: Ulemper: Krever god datakvalitet på tvers av fagsystemer (Unit4 ERP, SAP Lønn, FS).
... A70: Oppsummering for Senior Controller ved HHU
A71: Område | B71: Anbefalt Metode | C71: Hovedfokus / Styringssignal
A72: Lønn & Bemanning | B72: Driverbasert (UBW Planlegger) | C72: Stillingsgrupper, sosiale kostnader, 3–5 % vakansfaktor, 3–6 mnd rekrutteringstid.
A73: Utdanningsinntekter | B73: Driverbasert (KD 2025-modell) | C73: SPE60-produksjon, 2-års etterslep, Kategori 1 (54 550 kr) og nettobudsjettering.
A74: Ekstern Forskning (BOA) | B74: TDI-modellen | C74: Frikjøpsbalanse (buy-out), korrekt SRS 10-periodisering og full overhead-dekning.
A75: Løpende Oppfølging | B75: Rullende prognoser (LE) & Power BI | C75: T3 Cutoff, avviksdrivere, RAG-status og overvåking mot 5 %-regelen (F-05-20).

Sheet bud_metoder2
A1: I offentlig sektor og universitets- og høgskolesektoren (UH) har budsjettering beveget seg fra passiv historisk rammetildeling til strategisk virksomhetsstyring12. Nedenfor gis en gjennomgang av de mest sentrale budsjetteringsmetodene, følges opp av en konkret anbefaling for Handelshøyskolen ved UiA (HHU).
A4: 1. Oversikt over ulike budsjetteringsmetoder
A5: A. Historisk / Inkrementell budsjettering (Rammebudsjettering)
A7: Konsept: Fjorårets budsjett eller regnskap legges til grunn som baseline, og justeres marginalt opp eller ned basert på generell pris- og lønnsvekst (deflator) samt flate rammekutt (f.eks. ABE-kutt)12.
A8: Fordeler: Enkel å gjennomføre, krever lite ressursbruk.
A9: Ulemper: Konserverer historiske skjevheter, skjermer ineffektive aktiviteter og fanger i liten grad opp reelle endringer i studieproduksjon eller bemanningsstruktur12.
A11: B. Driverbasert budsjettering (Driver-Based Budgeting)
A13: Konsept: Budsjettet bygges opp fra underliggende operasjonelle volum- og aktivitetsdrivere23.
A14: Inntektssiden styres av KDs finansieringsmodell (antall avlagte studiepoeng/SPE60, kandidater og PhD-er)23.
A15: Kostnadssiden styres av antall årsverk (UF/TA), lønnstrinn, sosiale kostnader, antall emner og undervisningstimer34.
A16: Fordeler: Høy presisjon, direkte kobling mellom faglig aktivitet og økonomisk konsekvens, og mulighet for årsakssammenhengende avviksanalyser (volum- vs. prisavvik)45.
A17: Ulemper: Krever god datakvalitet på tvers av fagsystemer (Unit4 ERP, SAP Lønn, FS)46.
... A70: Oppsummering for Senior Controller ved HHU
A71: Område | B71: Anbefalt Metode | C71: Hovedfokus / Styringssignal
A72: Lønn & Bemanning | B72: Driverbasert (UBW Planlegger) | C72: Stillingsgrupper, sosiale kostnader, 3–5 % vakansfaktor, 3–6 mnd rekrutteringstid34.
A73: Utdanningsinntekter | B73: Driverbasert (KD 2025-modell) | C73: SPE60-produksjon, 2-års etterslep, Kategori 1 (54 550 kr) og nettobudsjettering2more_horiz.
A74: Ekstern Forskning (BOA) | B74: TDI-modellen | C74: Frikjøpsbalanse (buy-out), korrekt SRS 10-periodisering og full overhead-dekning4more_horiz.
A75: Løpende Oppfølging | B75: Rullende prognoser (LE) & Power BI | C75: T3 Cutoff, avviksdrivere, RAG-status og overvåking mot 5 %-regelen (F-05-20)4more_horiz.
A76: keep_pinSave to notekeep_pin
A77: copy
A78: thumb_up
A79: thumb_down
A81: Forklar 2025-finansieringsmodellen
A83: Thoughts
A84: expand_more
A85: Kunnskapsdepartementets (KD) finansieringsmodell fra 2025 innebærer en forenkling og omlegging av statens tildelingssystem for universiteter og høyskoler12. Modellen flytter tyngdepunktet mot en styrket basisbevilgning kombinert med en rendyrket åpen resultatramme knyttet til utdanningsproduksjon1more_horiz.
A88: 1. Hovedkomponentene i 2025-modellen
A90: 1. Styrket basisbevilgning (Avvikling av lukkede resultatrammer):
A91: Tidligere «lukkede resultatindikatorer» for forskningspublisering (publiseringspoeng), inntekter fra Norges forskningsråd (NFR), EU (Horisont Europa) og øvrig bidrags- og oppdragsaktivitet (BOA) er avviklet som egne løpende resultatindikatorer i den nasjonale modellen12.
A92: Disse resultatmidlene er i stedet innlemmet i den faste basisbevilgningen basert på et treårig historisk gjennomsnitt (2020–2022)12. Dette gir økt forutsigbarhet, men innebærer også at den automatiske statlige «skurtresker-effekten» for nye publiseringspoeng faller bort13.
... A160: 3. Tidsforskyvning og treghet: Et produksjonsfall i 2025 gir ikke umiddelbar regnskapseffekt i 2025 eller 2026, men skaper et forsinket bevilgningshull i 20272more_horiz. Controlleren må derfor advare ledelsen om denne effekten to år før regningen faktisk kommer34.

Sheet meta_data2
A1: Oversikt over genererte CSV-filer for Budsjett 2027
A2: Settet med 9 CSV-filer er bygget med semi-kolon (;) som skilletegn og UTF-8 med BOM for direkte import i Power BI Desktop:
A4: 1. FactBudget_2027.csv: Detaljert månedsperiodisert årsbudsjett (BUD2027) for alle 12 måneder i 2027 fordelt på kontoplan R-102 og organisasjonsenheter. Reflekterer HHUs samlede ramme på 286,8 MNOK i inntekter og 282,0 MNOK i kostnader (+4,8 MNOK i netto overskudd) samt UiAs totalramme (ca. 1 500 MNOK).
A5: 2. FactFTE_2027.csv: Bemannings- og årsverksplan for 2027. For HHU inngår 155 UF-årsverk (vitenskapelige), 75 TA-årsverk (teknisk-administrative), totalt 230 årsverk (252 ansatte), med innlagt 3–5 % vakansfaktor og snittlønnsdata.
A6: 3. FactStudents_2027.csv: Utdannings- og studiepoengmodell for 2027. Dokumenterer 2-års etterslep (lag) der 2025-produksjonen (3 120 SPE60) styrer resultatutbetalingen i 2027 basert på KDs Kategori 1-sats (54 550 kr/SPE60) for HHU, samt lærertetthet (22,3 stud/UF-ÅV).
A7: 4. FactAction_2027.csv: Omstillingstiltak T001–T004 for 2027 (frys i administrativ rekruttering, faglige omdisponeringer, EVU-ekspansjon) koblet mot regnskapslinjer og ansvarlige roller.
A8: 5. DimOrganization.csv: UiA organisasjonsstruktur (Toppnivå UiA, HHU og øvrige fakulteter, samt HHUs tre institutter og fakultetsadministrasjon).
A9: 6. DimAccountHierarchy.csv: Denormalisert kontoplan iht. DFØ R-102 og SRS-regnskapslinjer.
A10: 7. DimDate_2027.csv: Kalenderdimensjon for 2027 som markerer hele året som plan/budsjettperiode (ErActualYTD = FALSE). | R10: I statlig økonomistyring og ved Universiteter og høyskoler (UiA) brukes vakans og relaterte begreper om ubesatte stillinger og hvordan disse styres i bemannings- og lønnsbudsjettet:
A11: 8. DimForecastVersion.csv: Versjonstabell (BUD2027, PROG2028, PROG2029, PROG2030, PROG2031).
A12: 9. Relationships.csv: Kardinalitets- og kryssfiltreringstabell ($1:*$ enveisrelasjoner) for oppsett av datamodellen. | R12: Vakans (ledig stilling): En ubesatt stilling i organisasjonen som oppstår ved at en ansatt slutter, går av med pensjon, har ulønnet permisjon, eller at det opprettes en ny stillingshjemmel som ennå ikke er besatt.
R13: Vakansfaktor (vakansreduksjon): En innlagt sjablongmessig reduksjon i lønnsbudsjettet (typisk 3–5 %) i budsjetteringssystemer som Unit4 UBW Planlegger. Dette gjøres fordi det i praksis alltid vil ta tid (typisk 3–6 måneder) å rekruttere nye ansatte, samt at det løpende oppstår naturlig avgang og permisjoner. Uten en vakansfaktor vil lønnskostnadene bli overbudsjettert dersom man forutsetter 100 % full bemanning fra 1. januar til 31. desember.
R14: Vakansstyring: Controllerens og ledelsens aktive oppfølging av ledige stillinger. Dette innebærer å vurdere realistisk ansettelsestidspunkt, eller vurdering av om en stilling skal holdes midlertidig vakant (f.eks. ved ansettelsesstopp / tiltak T001) for å redusere personalkostnader og gjennopprette økonomisk balanse.
A16: 2. Data Model Diagram (Power BI Star Schema 2027) | R16: 💡 Sluttsum for controlleren: Lønn utgjør over 65–70 % av universitetets kostnader, så presis vakansstyring er det viktigste verktøyet for å styre personalkostnadene
A17: Bildet powerbi_datamodel_2027_diagram.png viser oppsettet av semantikkmodellen i Power BI.
A18: Datamodellen er bygget som et renskåret Stjerneskjema (Star Schema) hvor dimensjonstabellene filtrerer faktatabellene med enveis $1:*$-relasjoner:
A20: +---------------------------------------------------------------------------------------------------+
A21: | POWER BI SEMANTIC DATA MODEL — UiA & HHU BUDSJETT 2027 (STAR SCHEMA) |
A22: +---------------------------------------------------------------------------------------------------+
A24: [ DimOrganization ] [ DimAccountHierarchy ] [ DimDate_2027 ] [ DimForecastVersion ]
A25: (PK: OrgKode) (PK: Konto) (PK: DatoNokkel) (PK: VersjonKode)
A26: │ │ │ │
A27: │ (1) │ (1) │ (1) │ (1)
A28: │ │ │ │
A29: ├──────────────────────────┼───────────────────────────┼──────────────────────┘
A30: │ │ │
... A91: RAG-status: Trafikklysklassifisering (🟢 Grønn = I budsjett, 🟡 Gul = 2–5 % avvik, 🔴 Rød = > 5 % avvik).

Sheet DimAccountHierarchy
A1: Konto | B1: Kontonavn | C1: Nivaa1_Navn | D1: Kontotype | E1: SRS_regnskapslinje
A2: 3900 | B2: Inntekt fra bevilgninger (Basis) | C2: Salgs- og driftsinntekt | D2: Inntekt | E2: Inntekt fra bevilgninger
A3: 3400 | B3: Tilskudd fra NFR (Bidrag) | C3: Salgs- og driftsinntekt | D3: Inntekt | E3: Tilskudd og overføringer
A4: 3420 | B4: Tilskudd fra EU (Bidrag) | C4: Salgs- og driftsinntekt | D4: Inntekt | E4: Tilskudd og overføringer
A5: 3600 | B5: Oppdrags- og EVU-inntekter | C5: Salgs- og driftsinntekt | D5: Inntekt | E5: Salgsinntekt
A6: 5000 | B6: Lønn fast ansatte | C6: Lønnskostnad | D6: Kostnad | E6: Lønnskostnader
A7: 5050 | B7: Overtid og ekstraundervisning | C7: Lønnskostnad | D7: Kostnad | E7: Lønnskostnader
A8: 5100 | B8: Lønn midlertidig ansatte & timelærere | C8: Lønnskostnad | D8: Kostnad | E8: Lønnskostnader
A9: 5080 | B9: Feriepenger | C9: Lønnskostnad | D9: Kostnad | E9: Lønnskostnader
A10: 5400 | B10: Arbeidsgiveravgift | C10: Lønnskostnad | D10: Kostnad | E10: Lønnskostnader
A11: 5420 | B11: Pensjonspremie til SPK | C11: Lønnskostnad | D11: Kostnad | E11: Lønnskostnader
A12: 5800 | B12: Refusjon av sykepenger (NAV) | C12: Lønnskostnad | D12: Kostnad | E12: Lønnskostnader
A13: 6300 | B13: Leie lokaler & Arbeidsplass-sats | C13: Annen driftskostnad | D13: Kostnad | E13: Andre driftskostnader
... A21: 1250 | B21: Strategiske investeringer | C21: Annen driftskostnad | D21: Kostnad | E21: Andre driftskostnader

Sheet DimDate
A1: DatoNokkel | B1: Aar | C1: MaanedNummer | D1: MaanedNavn | E1: MaanedNavnKort | F1: Kvartal | G1: ErActualYTD | H1: PeriodeBeskrivelse | I1: Dato
A2: 202601 | B2: 2026 | C2: 1 | D2: Januar | E2: Jan | F2: Q1 | G2: TRUE | H2: Actual YTD (M01-M09) | I2: 46053
A3: 202602 | B3: 2026 | C3: 2 | D3: Februar | E3: Feb | F3: Q1 | G3: TRUE | H3: Actual YTD (M01-M09) | I3: 46081
A4: 202603 | B4: 2026 | C4: 3 | D4: Mars | E4: Mar | F4: Q1 | G4: TRUE | H4: Actual YTD (M01-M09) | I4: 46112
A5: 202604 | B5: 2026 | C5: 4 | D5: April | E5: Apr | F5: Q2 | G5: TRUE | H5: Actual YTD (M01-M09) | I5: 46142
A6: 202605 | B6: 2026 | C6: 5 | D6: Mai | E6: Mai | F6: Q2 | G6: TRUE | H6: Actual YTD (M01-M09) | I6: 46173
A7: 202606 | B7: 2026 | C7: 6 | D7: Juni | E7: Jun | F7: Q2 | G7: TRUE | H7: Actual YTD (M01-M09) | I7: 46203
A8: 202607 | B8: 2026 | C8: 7 | D8: Juli | E8: Jul | F8: Q3 | G8: TRUE | H8: Actual YTD (M01-M09) | I8: 46234
A9: 202608 | B9: 2026 | C9: 8 | D9: August | E9: Aug | F9: Q3 | G9: TRUE | H9: Actual YTD (M01-M09) | I9: 46265
A10: 202609 | B10: 2026 | C10: 9 | D10: September | E10: Sep | F10: Q3 | G10: TRUE | H10: Actual YTD (M01-M09) | I10: 46295
A11: 202610 | B11: 2026 | C11: 10 | D11: Oktober | E11: Okt | F11: Q4 | G11: FALSE | H11: Forecast Q4 (M10-M12) | I11: 46326
A12: 202611 | B12: 2026 | C12: 11 | D12: November | E12: Nov | F12: Q4 | G12: FALSE | H12: Forecast Q4 (M10-M12) | I12: 46356
A13: 202612 | B13: 2026 | C13: 12 | D13: Desember | E13: Des | F13: Q4 | G13: FALSE | H13: Forecast Q4 (M10-M12) | I13: 46387

Sheet DimDate_2027
A1: DatoNokkel | B1: Dato | C1: Aar | D1: MaanedNummer | E1: MaanedNavn | F1: MaanedNavnKort | G1: Kvartal | H1: ErActualYTD | I1: Budsjettaar
A2: 20270131 | B2: 46418 | C2: 2027 | D2: 1 | E2: January | F2: Jan | G2: Q1 | H2: FALSE | I2: 2027
A3: 20270228 | B3: 46446 | C3: 2027 | D3: 2 | E3: February | F3: Feb | G3: Q1 | H3: FALSE | I3: 2027
A4: 20270331 | B4: 46477 | C4: 2027 | D4: 3 | E4: March | F4: Mar | G4: Q1 | H4: FALSE | I4: 2027
A5: 20270430 | B5: 46507 | C5: 2027 | D5: 4 | E5: April | F5: Apr | G5: Q2 | H5: FALSE | I5: 2027
A6: 20270531 | B6: 46538 | C6: 2027 | D6: 5 | E6: May | F6: May | G6: Q2 | H6: FALSE | I6: 2027
A7: 20270630 | B7: 46568 | C7: 2027 | D7: 6 | E7: June | F7: Jun | G7: Q2 | H7: FALSE | I7: 2027
A8: 20270731 | B8: 46599 | C8: 2027 | D8: 7 | E8: July | F8: Jul | G8: Q3 | H8: FALSE | I8: 2027
A9: 20270831 | B9: 46630 | C9: 2027 | D9: 8 | E9: August | F9: Aug | G9: Q3 | H9: FALSE | I9: 2027
A10: 20270930 | B10: 46660 | C10: 2027 | D10: 9 | E10: September | F10: Sep | G10: Q3 | H10: FALSE | I10: 2027
A11: 20271031 | B11: 46691 | C11: 2027 | D11: 10 | E11: October | F11: Oct | G11: Q4 | H11: FALSE | I11: 2027
A12: 20271130 | B12: 46721 | C12: 2027 | D12: 11 | E12: November | F12: Nov | G12: Q4 | H12: FALSE | I12: 2027
A13: 20271231 | B13: 46752 | C13: 2027 | D13: 12 | E13: December | F13: Dec | G13: Q4 | H13: FALSE | I13: 2027

Sheet DimForecastVersion
A1: VersjonKode | B1: VersjonNavn | C1: Status | D1: SisteOppdatert
A2: BUD2026 | B2: Vedtatt Årsbudsjett 2026 | C2: Låst Baseline | D2: 46006
A3: ACTUAL_YTD_SEP2026 | B3: Regnskap YTD 30.09.2026 | C3: Bokført (Actual) | D3: 46295
A4: FC_Q4_2026 | B4: Prognose Q4 2026 (ETC) | C4: Rullende Estimering | D4: 46295
A5: LE_2026 | B5: Helårsprognose Latest Estimate (EAC) | C5: Gjeldende Sluttprognose | D5: 46295
A6: BUD2027 | B6: Vedtatt årsbudsjett 2027 | C6: Låst Baseline | D6: 46293

Sheet DimOrganization
A1: OrgKode | B1: Enhetsnavn | C1: Nivaa1 | D1: Nivaa2 | E1: Nivaa3 | F1: Budsjettansvarlig | G1: LederTittel | H1: Virksomhetstype
A2: K10000 | B2: HHU Fakultetsadministrasjon & Felles | C2: UiA | D2: Handelshøyskolen ved UiA (HHU) | E2: Fakultetsadministrasjon | F2: Fakultetsdirektør Kristian Jørgensen | G2: Fakultetsdirektør | H2: Drift
A3: K11000 | B3: Institutt for ledelse og innovasjon | C3: UiA | D3: Handelshøyskolen ved UiA (HHU) | E3: Institutt for ledelse og innovasjon | F3: Instituttleder Ledelse | G3: Instituttleder | H3: Drift/BOA
A4: K12000 | B4: Institutt for rettsvitenskap | C4: UiA | D4: Handelshøyskolen ved UiA (HHU) | E4: Institutt for rettsvitenskap | F4: Instituttleder Ole Dag Rike | G4: Instituttleder | H4: Drift
A5: K13000 | B5: Institutt for økonomi | C5: UiA | D5: Handelshøyskolen ved UiA (HHU) | E5: Institutt for økonomi | F5: Instituttleder Økonomi | G5: Instituttleder | H5: Drift/BOA

Sheet Relationships
A1: FraTabell | B1: FraKolonne | C1: TilTabell | D1: TilKolonne | E1: Kardinalitet | F1: Kryssfiltrering
A2: FactBudget | B2: OrgKode | C2: DimOrganization | D2: OrgKode | E2: *:1 | F2: Single
A3: FactBudget | B3: Konto | C3: DimAccountHierarchy | D3: Konto | E3: *:1 | F3: Single
A4: FactBudget | B4: DatoNokkel | C4: DimDate | D4: DatoNokkel | E4: *:1 | F4: Single
A5: FactGL | B5: OrgKode | C5: DimOrganization | D5: OrgKode | E5: *:1 | F5: Single
A6: FactGL | B6: Konto | C6: DimAccountHierarchy | D6: Konto | E6: *:1 | F6: Single
A7: FactGL | B7: DatoNokkel | C7: DimDate | D7: DatoNokkel | E7: *:1 | F7: Single
A8: FactFTE | B8: OrgKode | C8: DimOrganization | D8: OrgKode | E8: *:1 | F8: Single
A9: FactFTE | B9: DatoNokkel | C9: DimDate | D9: DatoNokkel | E9: *:1 | F9: Single
A10: FactStudents | B10: OrgKode | C10: DimOrganization | D10: OrgKode | E10: *:1 | F10: Single
A11: FactEVM | B11: DatoNokkel | C11: DimDate | D11: DatoNokkel | E11: *:1 | F11: Single
A12: FactAction | B12: OrgKode | C12: DimOrganization | D12: OrgKode | E12: *:1 | F12: Single
... A23: FactBudget_2027 | B23: VersjonKode | C23: DimForecastVersion | D23: VersjonKode | E23: *:1 | F23: Single

Sheet FactAction
A1: TiltakID | B1: OrgKode | C1: Budsjettansvarsområde | D1: AnsvarligLeder | E1: TiltakNavn | F1: ForventetInnsparingNOK | G1: RealisertInnsparingNOK | H1: Status | I1: FristDato
A2: T001_HHU | B2: K10000 | C2: Fakultetsadministrasjon | D2: Fakultetsdirektør Kristian Jørgensen | E2: Frys i ikke-kritisk administrativ rekruttering (TA) | F2: 1200000 | G2: 950000 | H2: Gjennomført | I2: 46387
A3: T002_HHU | B3: K13000 | C3: Inst. Økonomi | D3: Instituttleder Økonomi | E3: Økt overføring av vitenskapelig tid til BOA frikjøp (NFR/EU) | F3: 1800000 | G3: 1400000 | H3: Pågår | I3: 46387
A4: T003_HHU | B4: K11000 | C4: Inst. Ledelse & Innovasjon | D4: Instituttleder Ledelse | E4: Lønnsomhetskorrigering og prosjektkontroll på EVU001 (SRS 9) | F4: 800000 | G4: 450000 | H4: Pågår | I4: 46356
A5: T004_HHU | B5: K12000 | C5: Inst. Rettsvitenskap | D5: Instituttleder Ole Dag Rike | E5: Midlertidig vakanshold av professorhjemmel i Q2-Q3 | F5: 800000 | G5: 800000 | H5: Gjennomført | I5: 46295

Sheet FactAction_2027
A1: TiltakID | B1: OrgKode | C1: Tiltaksnavn | D1: Kategori | E1: Ansvarlig | F1: ForventetEffekt | G1: RealisertEffekt | H1: Status | I1: Beskrivelse
A2: T001_2027 | B2: K10000 | C2: Frys i administrativ rekruttering (TA-årsverk) | D2: Lønnskostnad | E2: Kristian Jørgensen | F2: 1800000 | G2: 1800000 | H2: 🟢 Gjennomført | I2: Holde 2 TA-stillinger ubesatt i Q1-Q2 2027 for å dempe lønnsvekst
A3: T002_2027 | B3: K13000 | C3: Strategisk reallokering av faglige UF-hjemler | D3: Lønnskostnad | E3: Instituttleder Økonomi | F3: 1500000 | G3: 1500000 | H3: 🟢 I rute | I3: Overføre 2,0 UF-årsverk fra lavere etterspurt emneportefølje til Siviløkonom M-SIVØK
A4: T003_2027 | B4: K11000 | C4: Ekspansjon i oppdragsutdanning (EVU Master HR) | D4: Inntekt (SRS 9) | E4: Instituttleder Ledelse | F4: 1400000 | G4: 1400000 | H4: 🟢 I rute | I4: Lansering av ny modulbasert ledelsesutdanning mot Sørlandets næringsliv
A5: T004_2027 | B5: K13000 | C5: TDI Research Buy-out vekst (NFR/EU Frikjøp) | D5: Inntekt (SRS 10) | E5: Forskningsleder HHU | F5: 1800000 | G5: 1800000 | H5: 🟢 I rute | I5: Øke eksternt frikjøp med 3,0 UF-årsverk for å sikre ~22% TDI overhead-refusjon

Sheet FactEVM
A1: DatoNokkel | B1: BAC_BudgetAtCompletion | C1: PlannedValue_PV | D1: EarnedValue_EV | E1: ActualCost_AC | F1: EstimateAtCompletion_EAC | G1: EstimateToComplete_ETC | H1: VarianceAtCompletion_VAC | I1: CostPerformanceIndex_CPI | J1: SchedulePerformanceIndex_SPI
A2: 202601 | B2: 130153825 | C2: 10846152 | D2: 10520768 | E2: 11063075 | F2: 131450000 | G2: 1.2038692e+08 | H2: -1296175 | I2: 0.951 | J2: 0.97
A3: 202602 | B3: 130153825 | C3: 21692304 | D3: 21041535 | E3: 22126150 | F3: 131450000 | G3: 1.0932385e+08 | H3: -1296175 | I3: 0.951 | J3: 0.97
A4: 202603 | B4: 130153825 | C4: 32538456 | D4: 31562303 | E4: 33189225 | F4: 131450000 | G4: 98260775 | H4: -1296175 | I4: 0.951 | J4: 0.97
A5: 202604 | B5: 130153825 | C5: 43384608 | D5: 42083070 | E5: 44252300 | F5: 131450000 | G5: 87197700 | H5: -1296175 | I5: 0.951 | J5: 0.97
A6: 202605 | B6: 130153825 | C6: 54230760 | D6: 52603838 | E6: 55315376 | F6: 131450000 | G6: 76134624 | H6: -1296175 | I6: 0.951 | J6: 0.97
A7: 202606 | B7: 130153825 | C7: 65076912 | D7: 63124605 | E7: 66378451 | F7: 131450000 | G7: 65071549 | H7: -1296175 | I7: 0.951 | J7: 0.97
A8: 202607 | B8: 130153825 | C8: 75923065 | D8: 73645373 | E8: 77441526 | F8: 131450000 | G8: 54008474 | H8: -1296175 | I8: 0.951 | J8: 0.97
A9: 202608 | B9: 130153825 | C9: 86769217 | D9: 84166140 | E9: 88504601 | F9: 131450000 | G9: 42945399 | H9: -1296175 | I9: 0.951 | J9: 0.97
A10: 202609 | B10: 130153825 | C10: 97615369 | D10: 94686908 | E10: 99567676 | F10: 131450000 | G10: 31882324 | H10: -1296175 | I10: 0.951 | J10: 0.97
A11: 202610 | B11: 130153825 | C11: 1.0846152e+08 | D11: 1.0629229e+08 | E11: 1.0954614e+08 | F11: 131450000 | G11: 21903864 | H11: -1296175 | I11: 0.97 | J11: 0.98
A12: 202611 | B12: 130153825 | C12: 1.1930767e+08 | D12: 1.1692152e+08 | E12: 1.2050075e+08 | F12: 131450000 | G12: 10949250 | H12: -1296175 | I12: 0.97 | J12: 0.98
A13: 202612 | B13: 130153825 | C13: 130153825 | D13: 1.2755075e+08 | E13: 1.3145536e+08 | F13: 131450000 | G13: -5363.25 | H13: -1296175 | I13: 0.97 | J13: 0.98

Sheet FactFTE
A1: DatoNokkel | B1: OrgKode | C1: Budsjettansvarsområde | D1: BudsjettansvarligLeder | E1: Aarsverk_UF | F1: Aarsverk_TA | G1: Aarsverk_Totalt | H1: Budsjettert_Aarsverk | I1: Vakans_Aarsverk | J1: Antall_Ansatte | K1: Vakansgrad_Pct
A2: 202601 | B2: K10000 | C2: HHU Fakultetsadministrasjon & Felles | D2: Fakultetsdirektør Kristian Jørgensen | E2: 0 | F2: 21.5 | G2: 21.5 | H2: 22 | I2: 0.5 | J2: 24 | K2: 2.27
A3: 202601 | B3: K11000 | C3: Institutt for ledelse og innovasjon | D3: Instituttleder Ledelse | E3: 45 | F3: 18 | G3: 63 | H3: 63 | I3: 0 | J3: 68 | K3: 0
A4: 202601 | B4: K12000 | C4: Institutt for rettsvitenskap | D4: Instituttleder Ole Dag Rike | E4: 35 | F4: 12 | G4: 47 | H4: 48 | I4: 1 | J4: 50 | K4: 2.08
A5: 202601 | B5: K13000 | C5: Institutt for økonomi | D5: Instituttleder Økonomi | E5: 75 | F5: 23 | G5: 98 | H5: 97 | I5: -1 | J5: 110 | K5: -1.03
A6: 202602 | B6: K10000 | C6: HHU Fakultetsadministrasjon & Felles | D6: Fakultetsdirektør Kristian Jørgensen | E6: 0 | F6: 21.5 | G6: 21.5 | H6: 22 | I6: 0.5 | J6: 24 | K6: 2.27
A7: 202602 | B7: K11000 | C7: Institutt for ledelse og innovasjon | D7: Instituttleder Ledelse | E7: 45 | F7: 18 | G7: 63 | H7: 63 | I7: 0 | J7: 68 | K7: 0
A8: 202602 | B8: K12000 | C8: Institutt for rettsvitenskap | D8: Instituttleder Ole Dag Rike | E8: 35 | F8: 12 | G8: 47 | H8: 48 | I8: 1 | J8: 50 | K8: 2.08
A9: 202602 | B9: K13000 | C9: Institutt for økonomi | D9: Instituttleder Økonomi | E9: 75 | F9: 23 | G9: 98 | H9: 97 | I9: -1 | J9: 110 | K9: -1.03
A10: 202603 | B10: K10000 | C10: HHU Fakultetsadministrasjon & Felles | D10: Fakultetsdirektør Kristian Jørgensen | E10: 0 | F10: 21.5 | G10: 21.5 | H10: 22 | I10: 0.5 | J10: 24 | K10: 2.27
A11: 202603 | B11: K11000 | C11: Institutt for ledelse og innovasjon | D11: Instituttleder Ledelse | E11: 45 | F11: 18 | G11: 63 | H11: 63 | I11: 0 | J11: 68 | K11: 0
A12: 202603 | B12: K12000 | C12: Institutt for rettsvitenskap | D12: Instituttleder Ole Dag Rike | E12: 35 | F12: 12 | G12: 47 | H12: 48 | I12: 1 | J12: 50 | K12: 2.08
A13: 202603 | B13: K13000 | C13: Institutt for økonomi | D13: Instituttleder Økonomi | E13: 75 | F13: 23 | G13: 98 | H13: 97 | I13: -1 | J13: 110 | K13: -1.03
... A49: 202612 | B49: K13000 | C49: Institutt for økonomi | D49: Instituttleder Økonomi | E49: 75 | F49: 23 | G49: 98 | H49: 97 | I49: -1 | J49: 110 | K49: -1.03

Sheet FactFTE_2027
A1: FTENokkel | B1: DatoNokkel | C1: OrgKode | D1: Budsjettert_Aarsverk | E1: Vakans_Aarsverk | F1: Aarsverk_Totalt | G1: Aarsverk_UF | H1: Aarsverk_TA | I1: Antall_Ansatte | J1: Maanedlig_Lonnskostnad | K1: Lennsandel_Pct
A2: FTE2027_20270131_K10000 | B2: 20270131 | C2: K10000 | D2: 30 | E2: 1.05 | F2: 28.95 | G2: 5 | H2: 25 | I2: 32 | J2: 1737000 | K2: 0.639
A3: FTE2027_20270131_K11000 | B3: 20270131 | C3: K11000 | D3: 63 | E3: 2.21 | F3: 60.79 | G3: 45 | H3: 18 | I3: 68 | J3: 4255300 | K3: 0.639
A4: FTE2027_20270131_K12000 | B4: 20270131 | C4: K12000 | D4: 50 | E4: 1.75 | F4: 48.25 | G4: 38 | H4: 12 | I4: 54 | J4: 3457916.7 | K4: 0.639
A5: FTE2027_20270131_K13000 | B5: 20270131 | C5: K13000 | D5: 87 | E5: 3.05 | F5: 83.95 | G5: 67 | H5: 20 | I5: 94 | J5: 6226291.7 | K5: 0.639
A6: FTE2027_20270228_K10000 | B6: 20270228 | C6: K10000 | D6: 30 | E6: 1.05 | F6: 28.95 | G6: 5 | H6: 25 | I6: 32 | J6: 1737000 | K6: 0.639
A7: FTE2027_20270228_K11000 | B7: 20270228 | C7: K11000 | D7: 63 | E7: 2.21 | F7: 60.79 | G7: 45 | H7: 18 | I7: 68 | J7: 4255300 | K7: 0.639
A8: FTE2027_20270228_K12000 | B8: 20270228 | C8: K12000 | D8: 50 | E8: 1.75 | F8: 48.25 | G8: 38 | H8: 12 | I8: 54 | J8: 3457916.7 | K8: 0.639
A9: FTE2027_20270228_K13000 | B9: 20270228 | C9: K13000 | D9: 87 | E9: 3.05 | F9: 83.95 | G9: 67 | H9: 20 | I9: 94 | J9: 6226291.7 | K9: 0.639
A10: FTE2027_20270331_K10000 | B10: 20270331 | C10: K10000 | D10: 30 | E10: 1.05 | F10: 28.95 | G10: 5 | H10: 25 | I10: 32 | J10: 1737000 | K10: 0.639
A11: FTE2027_20270331_K11000 | B11: 20270331 | C11: K11000 | D11: 63 | E11: 2.21 | F11: 60.79 | G11: 45 | H11: 18 | I11: 68 | J11: 4255300 | K11: 0.639
A12: FTE2027_20270331_K12000 | B12: 20270331 | C12: K12000 | D12: 50 | E12: 1.75 | F12: 48.25 | G12: 38 | H12: 12 | I12: 54 | J12: 3457916.7 | K12: 0.639
A13: FTE2027_20270331_K13000 | B13: 20270331 | C13: K13000 | D13: 87 | E13: 3.05 | F13: 83.95 | G13: 67 | H13: 20 | I13: 94 | J13: 6226291.7 | K13: 0.639
... A49: FTE2027_20271231_K13000 | B49: 20271231 | C49: K13000 | D49: 87 | E49: 3.05 | F49: 83.95 | G49: 67 | H49: 20 | I49: 94 | J49: 6226291.7 | K49: 0.639

Sheet FactStudents
A1: StudentNokkel | B1: DatoNokkel | C1: OrgKode | D1: Studieprogram | E1: RegistrerteStudenter | F1: SPE60_Baseline_2025 | G1: SPE60_Vekst_2025 | H1: SPE60 | I1: KDKategori | J1: KDSats_NOK | K1: KD_Marginal_Inntekt_2027 | L1: Studenter_pr_UF
A2: STUD2027_20270131_K11000 | B2: 20270131 | C2: K11000 | D2: Master Org. & Ledelse / MKT | E2: 1150 | F2: 1040 | G2: 10 | H2: 1050 | I2: Kategori 1 | J2: 54550 | K2: 545500 | L2: 25.6
A3: STUD2027_20270131_K12000 | B3: 20270131 | C3: K12000 | D3: Master & Bachelor i Rettsvitenskap | E3: 850 | F3: 780 | G3: 8 | H3: 788 | I3: Kategori 1 | J3: 54550 | K3: 436400 | L3: 22.4
A4: STUD2027_20270131_K13000 | B4: 20270131 | C4: K13000 | D4: Siviløkonom / Øk.Ad / Ph.D. | E4: 1450 | F4: 1300 | G4: 15 | H4: 1315 | I4: Kategori 1 | J4: 54550 | K4: 818250 | L4: 21.6
A5: STUD2027_20270430_K11000 | B5: 20270430 | C5: K11000 | D5: Master Org. & Ledelse / MKT | E5: 1150 | F5: 1040 | G5: 10 | H5: 1050 | I5: Kategori 1 | J5: 54550 | K5: 545500 | L5: 25.6
A6: STUD2027_20270430_K12000 | B6: 20270430 | C6: K12000 | D6: Master & Bachelor i Rettsvitenskap | E6: 850 | F6: 780 | G6: 8 | H6: 788 | I6: Kategori 1 | J6: 54550 | K6: 436400 | L6: 22.4
A7: STUD2027_20270430_K13000 | B7: 20270430 | C7: K13000 | D7: Siviløkonom / Øk.Ad / Ph.D. | E7: 1450 | F7: 1300 | G7: 15 | H7: 1315 | I7: Kategori 1 | J7: 54550 | K7: 818250 | L7: 21.6
A8: STUD2027_20270731_K11000 | B8: 20270731 | C8: K11000 | D8: Master Org. & Ledelse / MKT | E8: 1150 | F8: 1040 | G8: 10 | H8: 1050 | I8: Kategori 1 | J8: 54550 | K8: 545500 | L8: 25.6
A9: STUD2027_20270731_K12000 | B9: 20270731 | C9: K12000 | D9: Master & Bachelor i Rettsvitenskap | E9: 850 | F9: 780 | G9: 8 | H9: 788 | I9: Kategori 1 | J9: 54550 | K9: 436400 | L9: 22.4
A10: STUD2027_20270731_K13000 | B10: 20270731 | C10: K13000 | D10: Siviløkonom / Øk.Ad / Ph.D. | E10: 1450 | F10: 1300 | G10: 15 | H10: 1315 | I10: Kategori 1 | J10: 54550 | K10: 818250 | L10: 21.6
A11: STUD2027_20271031_K11000 | B11: 20271031 | C11: K11000 | D11: Master Org. & Ledelse / MKT | E11: 1150 | F11: 1040 | G11: 10 | H11: 1050 | I11: Kategori 1 | J11: 54550 | K11: 545500 | L11: 25.6
A12: STUD2027_20271031_K12000 | B12: 20271031 | C12: K12000 | D12: Master & Bachelor i Rettsvitenskap | E12: 850 | F12: 780 | G12: 8 | H12: 788 | I12: Kategori 1 | J12: 54550 | K12: 436400 | L12: 22.4
A13: STUD2027_20271031_K13000 | B13: 20271031 | C13: K13000 | D13: Siviløkonom / Øk.Ad / Ph.D. | E13: 1450 | F13: 1300 | G13: 15 | H13: 1315 | I13: Kategori 1 | J13: 54550 | K13: 818250 | L13: 21.6

Sheet FactStudents_2027
A1: StudentNokkel | B1: DatoNokkel | C1: OrgKode | D1: Studieprogram | E1: RegistrerteStudenter | F1: SPE60_Baseline_2025 | G1: SPE60_Vekst_2025 | H1: SPE60 | I1: KDKategori | J1: KDSats_NOK | K1: KD_Marginal_Inntekt_2027 | L1: Studenter_pr_UF
A2: STUD2027_20270131_K11000 | B2: 20270131 | C2: K11000 | D2: Master Org. & Ledelse / MKT | E2: 1150 | F2: 1040 | G2: 10 | H2: 1050 | I2: Kategori 1 | J2: 54550 | K2: 545500 | L2: 25.6
A3: STUD2027_20270131_K12000 | B3: 20270131 | C3: K12000 | D3: Master & Bachelor i Rettsvitenskap | E3: 850 | F3: 780 | G3: 8 | H3: 788 | I3: Kategori 1 | J3: 54550 | K3: 436400 | L3: 22.4
A4: STUD2027_20270131_K13000 | B4: 20270131 | C4: K13000 | D4: Siviløkonom / Øk.Ad / Ph.D. | E4: 1450 | F4: 1300 | G4: 15 | H4: 1315 | I4: Kategori 1 | J4: 54550 | K4: 818250 | L4: 21.6
A5: STUD2027_20270430_K11000 | B5: 20270430 | C5: K11000 | D5: Master Org. & Ledelse / MKT | E5: 1150 | F5: 1040 | G5: 10 | H5: 1050 | I5: Kategori 1 | J5: 54550 | K5: 545500 | L5: 25.6
A6: STUD2027_20270430_K12000 | B6: 20270430 | C6: K12000 | D6: Master & Bachelor i Rettsvitenskap | E6: 850 | F6: 780 | G6: 8 | H6: 788 | I6: Kategori 1 | J6: 54550 | K6: 436400 | L6: 22.4
A7: STUD2027_20270430_K13000 | B7: 20270430 | C7: K13000 | D7: Siviløkonom / Øk.Ad / Ph.D. | E7: 1450 | F7: 1300 | G7: 15 | H7: 1315 | I7: Kategori 1 | J7: 54550 | K7: 818250 | L7: 21.6
A8: STUD2027_20270731_K11000 | B8: 20270731 | C8: K11000 | D8: Master Org. & Ledelse / MKT | E8: 1150 | F8: 1040 | G8: 10 | H8: 1050 | I8: Kategori 1 | J8: 54550 | K8: 545500 | L8: 25.6
A9: STUD2027_20270731_K12000 | B9: 20270731 | C9: K12000 | D9: Master & Bachelor i Rettsvitenskap | E9: 850 | F9: 780 | G9: 8 | H9: 788 | I9: Kategori 1 | J9: 54550 | K9: 436400 | L9: 22.4
A10: STUD2027_20270731_K13000 | B10: 20270731 | C10: K13000 | D10: Siviløkonom / Øk.Ad / Ph.D. | E10: 1450 | F10: 1300 | G10: 15 | H10: 1315 | I10: Kategori 1 | J10: 54550 | K10: 818250 | L10: 21.6
A11: STUD2027_20271031_K11000 | B11: 20271031 | C11: K11000 | D11: Master Org. & Ledelse / MKT | E11: 1150 | F11: 1040 | G11: 10 | H11: 1050 | I11: Kategori 1 | J11: 54550 | K11: 545500 | L11: 25.6
A12: STUD2027_20271031_K12000 | B12: 20271031 | C12: K12000 | D12: Master & Bachelor i Rettsvitenskap | E12: 850 | F12: 780 | G12: 8 | H12: 788 | I12: Kategori 1 | J12: 54550 | K12: 436400 | L12: 22.4
A13: STUD2027_20271031_K13000 | B13: 20271031 | C13: K13000 | D13: Siviløkonom / Øk.Ad / Ph.D. | E13: 1450 | F13: 1300 | G13: 15 | H13: 1315 | I13: Kategori 1 | J13: 54550 | K13: 818250 | L13: 21.6

Sheet FactBudget
A1: DatoNokkel | B1: OrgKode | C1: Konto | D1: VersjonKode | E1: BudsjettBelop | F1: Budsjettansvarsområde | G1: BudsjettansvarligLeder
A2: 202601 | B2: K10000 | C2: 5000 | D2: BUD2026 | E2: 676666 | F2: Fakultetsadministrasjon | G2: Fakultetsdirektør Kristian Jørgensen
A3: 202602 | B3: K10000 | C3: 5000 | D3: BUD2026 | E3: 676666 | F3: Fakultetsadministrasjon | G3: Fakultetsdirektør Kristian Jørgensen
A4: 202603 | B4: K10000 | C4: 5000 | D4: BUD2026 | E4: 676666 | F4: Fakultetsadministrasjon | G4: Fakultetsdirektør Kristian Jørgensen
A5: 202604 | B5: K10000 | C5: 5000 | D5: BUD2026 | E5: 676666 | F5: Fakultetsadministrasjon | G5: Fakultetsdirektør Kristian Jørgensen
A6: 202605 | B6: K10000 | C6: 5000 | D6: BUD2026 | E6: 676666 | F6: Fakultetsadministrasjon | G6: Fakultetsdirektør Kristian Jørgensen
A7: 202606 | B7: K10000 | C7: 5000 | D7: BUD2026 | E7: 676666 | F7: Fakultetsadministrasjon | G7: Fakultetsdirektør Kristian Jørgensen
A8: 202607 | B8: K10000 | C8: 5000 | D8: BUD2026 | E8: 676666 | F8: Fakultetsadministrasjon | G8: Fakultetsdirektør Kristian Jørgensen
A9: 202608 | B9: K10000 | C9: 5000 | D9: BUD2026 | E9: 676666 | F9: Fakultetsadministrasjon | G9: Fakultetsdirektør Kristian Jørgensen
A10: 202609 | B10: K10000 | C10: 5000 | D10: BUD2026 | E10: 676666 | F10: Fakultetsadministrasjon | G10: Fakultetsdirektør Kristian Jørgensen
A11: 202610 | B11: K10000 | C11: 5000 | D11: BUD2026 | E11: 676666 | F11: Fakultetsadministrasjon | G11: Fakultetsdirektør Kristian Jørgensen
A12: 202611 | B12: K10000 | C12: 5000 | D12: BUD2026 | E12: 676666 | F12: Fakultetsadministrasjon | G12: Fakultetsdirektør Kristian Jørgensen
A13: 202612 | B13: K10000 | C13: 5000 | D13: BUD2026 | E13: 676674 | F13: Fakultetsadministrasjon | G13: Fakultetsdirektør Kristian Jørgensen
... A433: 202612 | B433: K13000 | C433: 7130 | D433: BUD2026 | E433: 121015 | F433: Inst. Økonomi | G433: Instituttleder Økonomi

Sheet FactBudget_2027
A1: BudsjettNokkel | B1: DatoNokkel | C1: OrgKode | D1: Konto | E1: VersjonKode | F1: BudsjettBelop | G1: Valuta | H1: Kommentar
A2: BUD2027_20270131_K10000_3900 | B2: 20270131 | C2: K10000 | D2: 3900 | E2: BUD2027 | F2: 1125000 | G2: NOK | H2: Månedlig periodisert 2027-budsjett for K10000 konto 3900
A3: BUD2027_20270131_K10000_3670 | B3: 20270131 | C3: K10000 | D3: 3670 | E3: BUD2027 | F3: 105820.83 | G3: NOK | H3: Månedlig periodisert 2027-budsjett for K10000 konto 3670
A4: BUD2027_20270131_K10000_5000 | B4: 20270131 | C4: K10000 | D4: 5000 | E4: BUD2027 | F4: 666666.67 | G4: NOK | H4: Månedlig periodisert 2027-budsjett for K10000 konto 5000
A5: BUD2027_20270131_K10000_5400 | B5: 20270131 | C5: K10000 | D5: 5400 | E5: BUD2027 | F5: 150000 | G5: NOK | H5: Månedlig periodisert 2027-budsjett for K10000 konto 5400
A6: BUD2027_20270131_K10000_6420 | B6: 20270131 | C6: K10000 | D6: 6420 | E6: BUD2027 | F6: 208333.33 | G6: NOK | H6: Månedlig periodisert 2027-budsjett for K10000 konto 6420
A7: BUD2027_20270131_K10000_6700 | B7: 20270131 | C7: K10000 | D7: 6700 | E7: BUD2027 | F7: 100000 | G7: NOK | H7: Månedlig periodisert 2027-budsjett for K10000 konto 6700
A8: BUD2027_20270131_K10000_1250 | B8: 20270131 | C8: K10000 | D8: 1250 | E8: BUD2027 | F8: 83333.33 | G8: NOK | H8: Månedlig periodisert 2027-budsjett for K10000 konto 1250
A9: BUD2027_20270131_K11000_3900 | B9: 20270131 | C9: K11000 | D9: 3900 | E9: BUD2027 | F9: 5666666.7 | G9: NOK | H9: Månedlig periodisert 2027-budsjett for K11000 konto 3900
A10: BUD2027_20270131_K11000_3600 | B10: 20270131 | C10: K11000 | D10: 3600 | E10: BUD2027 | F10: 666666.67 | G10: NOK | H10: Månedlig periodisert 2027-budsjett for K11000 konto 3600
A11: BUD2027_20270131_K11000_3630 | B11: 20270131 | C11: K11000 | D11: 3630 | E11: BUD2027 | F11: 333333.33 | G11: NOK | H11: Månedlig periodisert 2027-budsjett for K11000 konto 3630
A12: BUD2027_20270131_K11000_5000 | B12: 20270131 | C12: K11000 | D12: 5000 | E12: BUD2027 | F12: 4000000 | G12: NOK | H12: Månedlig periodisert 2027-budsjett for K11000 konto 5000
A13: BUD2027_20270131_K11000_5400 | B13: 20270131 | C13: K11000 | D13: 5400 | E13: BUD2027 | F13: 916666.67 | G13: NOK | H13: Månedlig periodisert 2027-budsjett for K11000 konto 5400
... A385: BUD2027_20271231_K13000_1250 | B385: 20271231 | C385: K13000 | D385: 1250 | E385: BUD2027 | F385: 2166666.7 | G385: NOK | H385: Månedlig periodisert 2027-budsjett for K13000 konto 1250

Sheet FactGL
A1: TransaksjonID | B1: DatoNokkel | C1: OrgKode | D1: Konto | E1: Bokforingstype | F1: VersjonKode | G1: Belop_signert | H1: Budsjettansvarsområde | I1: BudsjettansvarligLeder | J1: ProsjektID | K1: Avvikstype_Beskrivelse
A2: TR2026_00001 | B2: 202601 | C2: K10000 | D2: 5000 | E2: Actual | F2: ACTUAL_YTD_SEP2026 | G2: 676666 | H2: Fakultetsadministrasjon | I2: Fakultetsdirektør Kristian Jørgensen | J2: DRIFT | K2: Normal drift
A3: TR2026_00002 | B3: 202602 | C3: K10000 | D3: 5000 | E3: Actual | F3: ACTUAL_YTD_SEP2026 | G3: 676666 | H3: Fakultetsadministrasjon | I3: Fakultetsdirektør Kristian Jørgensen | J3: DRIFT | K3: Normal drift
A4: TR2026_00003 | B4: 202603 | C4: K10000 | D4: 5000 | E4: Actual | F4: ACTUAL_YTD_SEP2026 | G4: 676666 | H4: Fakultetsadministrasjon | I4: Fakultetsdirektør Kristian Jørgensen | J4: DRIFT | K4: Normal drift
A5: TR2026_00004 | B5: 202604 | C5: K10000 | D5: 5000 | E5: Actual | F5: ACTUAL_YTD_SEP2026 | G5: 676666 | H5: Fakultetsadministrasjon | I5: Fakultetsdirektør Kristian Jørgensen | J5: DRIFT | K5: Normal drift
A6: TR2026_00005 | B6: 202605 | C6: K10000 | D6: 5000 | E6: Actual | F6: ACTUAL_YTD_SEP2026 | G6: 676666 | H6: Fakultetsadministrasjon | I6: Fakultetsdirektør Kristian Jørgensen | J6: DRIFT | K6: Normal drift
A7: TR2026_00006 | B7: 202606 | C7: K10000 | D7: 5000 | E7: Actual | F7: ACTUAL_YTD_SEP2026 | G7: 676666 | H7: Fakultetsadministrasjon | I7: Fakultetsdirektør Kristian Jørgensen | J7: DRIFT | K7: Normal drift
A8: TR2026_00007 | B8: 202607 | C8: K10000 | D8: 5000 | E8: Actual | F8: ACTUAL_YTD_SEP2026 | G8: 676666 | H8: Fakultetsadministrasjon | I8: Fakultetsdirektør Kristian Jørgensen | J8: DRIFT | K8: Normal drift
A9: TR2026_00008 | B9: 202608 | C9: K10000 | D9: 5000 | E9: Actual | F9: ACTUAL_YTD_SEP2026 | G9: 676666 | H9: Fakultetsadministrasjon | I9: Fakultetsdirektør Kristian Jørgensen | J9: DRIFT | K9: Normal drift
A10: TR2026_00009 | B10: 202609 | C10: K10000 | D10: 5000 | E10: Actual | F10: ACTUAL_YTD_SEP2026 | G10: 676666 | H10: Fakultetsadministrasjon | I10: Fakultetsdirektør Kristian Jørgensen | J10: DRIFT | K10: Normal drift
A11: TR2026_00010 | B11: 202610 | C11: K10000 | D11: 5000 | E11: Forecast | F11: FC_Q4_2026 | G11: 676666 | H11: Fakultetsadministrasjon | I11: Fakultetsdirektør Kristian Jørgensen | J11: DRIFT | K11: Normal drift
A12: TR2026_00011 | B12: 202611 | C12: K10000 | D12: 5000 | E12: Forecast | F12: FC_Q4_2026 | G12: 676666 | H12: Fakultetsadministrasjon | I12: Fakultetsdirektør Kristian Jørgensen | J12: DRIFT | K12: Normal drift
A13: TR2026_00012 | B13: 202612 | C13: K10000 | D13: 5000 | E13: Forecast | F13: FC_Q4_2026 | G13: 676674 | H13: Fakultetsadministrasjon | I13: Fakultetsdirektør Kristian Jørgensen | J13: DRIFT | K13: Normal drift
... A434: TR2026_99999 | B434: 202609 | C434: K11000 | D434: 7790 | E434: Actual | F434: ACTUAL_YTD_SEP2026 | G434: 350000 | H434: Inst. Ledelse & Innovasjon | I434: Instituttleder Ledelse | J434: EVU001 | K434: SRS 9 Avsetning for forventet tap på oppdrag (EVU001)

Sheet DAX Measures
A1: DAX Measure Catalog — UiA HHU 2026–2027
A2: Validert mot importerte kolonnenavn. Kopier målene til en egen _Measures-tabell i Power Pivot / Power BI.
A4: Display Folder | B4: Measure | C4: Format | D4: Status | E4: DAX
A5: _01 Accounting | B5: Actual YTD | C5: NOK | D5: Klar | E5: Actual YTD = CALCULATE(SUM('FactGL'[Belop_signert]), 'FactGL'[Bokforingstype] = "Actual")
A6: _01 Accounting | B6: Budsjett YTD | C6: NOK | D6: Klar | E6: Budsjett YTD = CALCULATE(SUM('FactBudget'[BudsjettBelop]), 'DimDate'[ErActualYTD] = TRUE())
A7: _01 Accounting | B7: Avvik YTD | C7: NOK | D7: Klar | E7: Avvik YTD = [Actual YTD] - [Budsjett YTD]
A8: _01 Accounting | B8: Avvik YTD % | C8: 0 | D8: Klar | E8: Avvik YTD % = DIVIDE([Avvik YTD], [Budsjett YTD], 0)
A9: _01 Accounting | B9: Monthly Actuals and Forecast | C9: NOK | D9: Klar | E9: Monthly Actuals and Forecast = VAR CurrentMonth = MAX('DimDate'[MaanedNummer]) RETURN IF(CurrentMonth <= 9, CALCULATE(SUM('FactGL'[Belop_signert]), 'FactGL'[Bokforingstype] = "Actual"), CALCULATE(SUM('FactGL'[Belop_signert]), 'FactGL'[Bokforingstype] = "Forecast"))
A10: _02 Forecast & LE | B10: Forecast Q4 (ETC) | C10: NOK | D10: Klar | E10: Forecast Q4 (ETC) = CALCULATE(SUM('FactGL'[Belop_signert]), 'FactGL'[Bokforingstype] = "Forecast")
A11: _02 Forecast & LE | B11: Forecast LE (EAC) | C11: NOK | D11: Klar | E11: Forecast LE (EAC) = [Actual YTD] + [Forecast Q4 (ETC)]
A12: _02 Forecast & LE | B12: Årsbudsjett (BAC) | C12: NOK | D12: Klar | E12: Årsbudsjett (BAC) = SUM('FactBudget'[BudsjettBelop])
A13: _02 Forecast & LE | B13: Sluttavvik (VAC) | C13: NOK | D13: Klar | E13: Sluttavvik (VAC) = [Årsbudsjett (BAC)] - [Forecast LE (EAC)]
A14: _02 Forecast & LE | B14: VAC % | C14: 0 | D14: Klar | E14: VAC % = DIVIDE([Sluttavvik (VAC)], [Årsbudsjett (BAC)], 0)
A15: _03 Temporal YoY & MoM | B15: Actual PM | C15: NOK | D15: Klar | E15: Actual PM = CALCULATE([Actual YTD], PREVIOUSMONTH('DimDate'[Dato]))
A16: _03 Temporal YoY & MoM | B16: Actual CM | C16: NOK | D16: Klar | E16: Actual CM = CALCULATE(SUM('FactGL'[Belop_signert]), 'FactGL'[Bokforingstype] = "Actual")
A17: _03 Temporal YoY & MoM | B17: Actual MoM | C17: NOK | D17: Klar | E17: Actual MoM = [Actual CM] - [Actual PM]
A18: _03 Temporal YoY & MoM | B18: Actual MoM % | C18: 0 | D18: Klar | E18: Actual MoM % = DIVIDE([Actual MoM], [Actual PM], 0)
A19: _03 Temporal YoY & MoM | B19: Actual PY | C19: NOK | D19: Krever 2025-data | E19: Actual PY = CALCULATE([Actual YTD], SAMEPERIODLASTYEAR('DimDate'[Dato]))
A20: _04 EVM | B20: Planned Value (PV) | C20: NOK | D20: Klar | E20: Planned Value (PV) = MAX('FactEVM'[PlannedValue_PV])
A21: _04 EVM | B21: Earned Value (EV) | C21: NOK | D21: Klar | E21: Earned Value (EV) = MAX('FactEVM'[EarnedValue_EV])
A22: _04 EVM | B22: Actual Cost (AC) | C22: NOK | D22: Klar | E22: Actual Cost (AC) = MAX('FactEVM'[ActualCost_AC])
A23: _04 EVM | B23: CPI | C23: 0 | D23: Klar | E23: CPI = DIVIDE([Earned Value (EV)], [Actual Cost (AC)], 1)
A24: _04 EVM | B24: SPI | C24: 0 | D24: Klar | E24: SPI = DIVIDE([Earned Value (EV)], [Planned Value (PV)], 1)
A25: _05 Staffing & FTE | B25: Totale Årsverk | C25: 0 | D25: Klar | E25: Totale Årsverk = VAR D = MAX('FactFTE'[DatoNokkel]) RETURN CALCULATE(SUM('FactFTE'[Aarsverk_Totalt]), 'FactFTE'[DatoNokkel] = D)
A26: _05 Staffing & FTE | B26: Faglige Årsverk (UF) | C26: 0 | D26: Klar | E26: Faglige Årsverk (UF) = VAR D = MAX('FactFTE'[DatoNokkel]) RETURN CALCULATE(SUM('FactFTE'[Aarsverk_UF]), 'FactFTE'[DatoNokkel] = D)
A27: _05 Staffing & FTE | B27: Teknisk-Admin Årsverk (TA) | C27: 0 | D27: Klar | E27: Teknisk-Admin Årsverk (TA) = VAR D = MAX('FactFTE'[DatoNokkel]) RETURN CALCULATE(SUM('FactFTE'[Aarsverk_TA]), 'FactFTE'[DatoNokkel] = D)
A28: _05 Staffing & FTE | B28: Faglig Andel % | C28: 0 | D28: Klar | E28: Faglig Andel % = DIVIDE([Faglige Årsverk (UF)], [Totale Årsverk], 0)
A29: _05 Staffing & FTE | B29: Vakansgrad % | C29: 0 | D29: Klar | E29: Vakansgrad % = VAR D = MAX('FactFTE'[DatoNokkel]) VAR B = CALCULATE(SUM('FactFTE'[Budsjettert_Aarsverk]), 'FactFTE'[DatoNokkel] = D) RETURN DIVIDE(B - [Totale Årsverk], B, 0)
A30: _06 Utdanning & SPE60 | B30: Registrerte Studenter 2027 | C30: 0 | D30: Klar | E30: Registrerte Studenter 2027 = VAR D = MAX('FactStudents_2027'[DatoNokkel]) RETURN CALCULATE(SUM('FactStudents_2027'[RegistrerteStudenter]), 'FactStudents_2027'[DatoNokkel] = D)
A31: _06 Utdanning & SPE60 | B31: Avlagte SPE60 2027 | C31: 0 | D31: Klar | E31: Avlagte SPE60 2027 = VAR D = MAX('FactStudents_2027'[DatoNokkel]) RETURN CALCULATE(SUM('FactStudents_2027'[SPE60]), 'FactStudents_2027'[DatoNokkel] = D)
A32: _06 Utdanning & SPE60 | B32: KD Kat 1 Resultatutbetaling 2027 | C32: NOK | D32: Klar | E32: KD Kat 1 Resultatutbetaling 2027 = VAR D = MAX('FactStudents_2027'[DatoNokkel]) RETURN CALCULATE(SUM('FactStudents_2027'[KD_Marginal_Inntekt_2027]), 'FactStudents_2027'[DatoNokkel] = D, 'FactStudents_2027'[KDKategori] = "Kategori 1")
A33: _07 Action Tracker | B33: Forventet Tiltakseffekt 2026 | C33: NOK | D33: Klar | E33: Forventet Tiltakseffekt 2026 = SUM('FactAction'[ForventetInnsparingNOK])
A34: _07 Action Tracker | B34: Realisert Tiltakseffekt 2026 | C34: NOK | D34: Klar | E34: Realisert Tiltakseffekt 2026 = SUM('FactAction'[RealisertInnsparingNOK])
A35: _07 Action Tracker | B35: Tiltak Realiseringsgrad 2026 % | C35: 0 | D35: Klar | E35: Tiltak Realiseringsgrad 2026 % = DIVIDE([Realisert Tiltakseffekt 2026], [Forventet Tiltakseffekt 2026], 0)
A36: _10 HHU 2027 Budsjett | B36: BUD2027 Inntekter HHU | C36: NOK | D36: Klar | E36: BUD2027 Inntekter HHU = CALCULATE(SUM('FactBudget_2027'[BudsjettBelop]), 'DimAccountHierarchy'[Kontotype] = "Inntekt", 'FactBudget_2027'[VersjonKode] = "BUD2027")
A37: _10 HHU 2027 Budsjett | B37: BUD2027 Kostnader HHU | C37: NOK | D37: Klar | E37: BUD2027 Kostnader HHU = CALCULATE(SUM('FactBudget_2027'[BudsjettBelop]), 'DimAccountHierarchy'[Kontotype] = "Kostnad", 'FactBudget_2027'[VersjonKode] = "BUD2027")
A38: _10 HHU 2027 Budsjett | B38: BUD2027 Netto Resultat HHU | C38: NOK | D38: Klar | E38: BUD2027 Netto Resultat HHU = [BUD2027 Inntekter HHU] - [BUD2027 Kostnader HHU]
A39: _10 HHU 2027 Budsjett | B39: HHU Lønnsandel 2027 % | C39: 0 | D39: Klar | E39: HHU Lønnsandel 2027 % = VAR L = CALCULATE(SUM('FactBudget_2027'[BudsjettBelop]), 'DimAccountHierarchy'[Nivaa1_Navn] = "Lønnskostnad") RETURN DIVIDE(L, [BUD2027 Inntekter HHU], 0)
A40: _08 RAG & Design | B40: HHU 2027 RAG Status Badge | C40: Text | D40: Klar | E40: HHU 2027 RAG Status Badge = VAR R = [BUD2027 Netto Resultat HHU] VAR L = [HHU Lønnsandel 2027 %] RETURN SWITCH(TRUE(), R >= 4000000 && L <= 0.645, "🟢 Sterk margin", R >= 0, "🟡 Moderat overskudd", "🔴 Underskudd / Høy lønnsandel")

Sheet Chart Data
A1: Måned | B1: Budsjett | C1: Regnskap / prognose | D1: Fase | F1: Enhet | G1: Budsjett | H1: Sluttavvik | J1: Driver | K1: Avvik
A2: Jan | B2: 10846144 | C2: 10725571 | D2: Actual | F2: Administrasjon | G2: 14000000 | H2: 87499 | J2: K13000 – Fast lønn | K2: ='Variance Actions'!F11 -> -982596
A3: Feb | B3: 10846144 | C3: 10725571 | D3: Actual | F3: Ledelse og innovasjon | G3: 38500000 | H3: -3496 | J3: K12000 – Fast lønn | K3: ='Variance Actions'!F12 -> 678600
A4: Mar | B4: 10846144 | C4: 10755321 | D4: Actual | F4: Rettsvitenskap | G4: 29250000 | H4: 1148940 | J4: K13000 – Feriepenger | K4: ='Variance Actions'!F13 -> 407439
A5: Apr | B5: 10846144 | C5: 10725571 | D5: Actual | F5: Økonomi | G5: 48403825 | H5: -710685 | J5: K11000 – Feriepenger | K5: ='Variance Actions'!F14 -> 404254
A6: Mai | B6: 10846144 | C6: 10744821 | D6: Actual | J6: K12000 – Feriepenger | K6: ='Variance Actions'!F15 -> 376740
A7: Jun | B7: 10846144 | C7: 11202192 | D7: Actual | J7: K11000 – EVU001 tapsavsetning | K7: ='Variance Actions'!F16 -> -350000
A8: Jul | B8: 10846144 | C8: 10725571 | D8: Actual | J8: K10000 – Feriepenger | K8: ='Variance Actions'!F17 -> 146999
A9: Aug | B9: 10846144 | C9: 10725571 | D9: Actual | J9: K13000 – Arbeidsgiveravgift | K9: ='Variance Actions'!F18 -> -135528
A10: Sep | B10: 10846144 | C10: 11124571 | D10: Actual | J10: K12000 – Arbeidsgiveravgift | K10: ='Variance Actions'!F19 -> 93600
A11: Okt | B11: 10846144 | C11: 10725571 | D11: Forecast | J11: K10000 – AACSB konsulent | K11: ='Variance Actions'!F20 -> -59500
A12: Nov | B12: 10846144 | C12: 10725571 | D12: Forecast | J12: K11000 – Midlertidig lønn | K12: ='Variance Actions'!F21 -> -57750
A13: Des | B13: 10846241 | C13: 10725665 | D13: Forecast
